[
  {
    "Name": "Antonio Brown",
    "Team": "PIT",
    "Position": "WR",
    "ByeWeek": 7,
    "Age": 30,
    "RushingYards": 5,
    "RushingTouchdowns": 0,
    "Receptions": 108,
    "ReceivingYards": 1543,
    "ReceivingTouchdowns": 10,
    "FantasyPoints": 214.8,
    "AverageDraftPosition": 5.9,
    "Rank": 1
  },
  {
    "Name": "DeAndre Hopkins",
    "Team": "HOU",
    "Position": "WR",
    "ByeWeek": 10,
    "Age": 26,
    "RushingYards": 0,
    "RushingTouchdowns": 0,
    "Receptions": 94,
    "ReceivingYards": 1284,
    "ReceivingTouchdowns": 10,
    "FantasyPoints": 186.4,
    "AverageDraftPosition": 11.1,
    "Rank": 2
  },
  {
    "Name": "Odell Beckham Jr",
    "Team": "NYG",
    "Position": "WR",
    "ByeWeek": 9,
    "Age": 25,
    "RushingYards": 14,
    "RushingTouchdowns": 0,
    "Receptions": 94,
    "ReceivingYards": 1291,
    "ReceivingTouchdowns": 11,
    "FantasyPoints": 196.5,
    "AverageDraftPosition": 12.9,
    "Rank": 3
  },
  {
    "Name": "Julio Jones",
    "Team": "ATL",
    "Position": "WR",
    "ByeWeek": 8,
    "Age": 29,
    "RushingYards": 6,
    "RushingTouchdowns": 0,
    "Receptions": 96,
    "ReceivingYards": 1501,
    "ReceivingTouchdowns": 6,
    "FantasyPoints": 186.7,
    "AverageDraftPosition": 14.3,
    "Rank": 4
  },
  {
    "Name": "Michael Thomas",
    "Team": "NO",
    "Position": "WR",
    "ByeWeek": 6,
    "Age": 25,
    "RushingYards": 4,
    "RushingTouchdowns": 0,
    "Receptions": 99,
    "ReceivingYards": 1238,
    "ReceivingTouchdowns": 9,
    "FantasyPoints": 178.2,
    "AverageDraftPosition": 17.1,
    "Rank": 5
  },
  {
    "Name": "Davante Adams",
    "Team": "GB",
    "Position": "WR",
    "ByeWeek": 7,
    "Age": 25,
    "RushingYards": 6,
    "RushingTouchdowns": 0,
    "Receptions": 90,
    "ReceivingYards": 1132,
    "ReceivingTouchdowns": 12,
    "FantasyPoints": 185.8,
    "AverageDraftPosition": 18.4,
    "Rank": 6
  },
  {
    "Name": "Keenan Allen",
    "Team": "LAC",
    "Position": "WR",
    "ByeWeek": 8,
    "Age": 26,
    "RushingYards": 5,
    "RushingTouchdowns": 0,
    "Receptions": 94,
    "ReceivingYards": 1224,
    "ReceivingTouchdowns": 8,
    "FantasyPoints": 170.9,
    "AverageDraftPosition": 20.3,
    "Rank": 7
  },
  {
    "Name": "AJ Green",
    "Team": "CIN",
    "Position": "WR",
    "ByeWeek": 9,
    "Age": 30,
    "RushingYards": 0,
    "RushingTouchdowns": 0,
    "Receptions": 83,
    "ReceivingYards": 1214,
    "ReceivingTouchdowns": 9,
    "FantasyPoints": 173.4,
    "AverageDraftPosition": 21.8,
    "Rank": 8
  },
  {
    "Name": "Mike Evans",
    "Team": "TB",
    "Position": "WR",
    "ByeWeek": 5,
    "Age": 24,
    "RushingYards": 0,
    "RushingTouchdowns": 0,
    "Receptions": 80,
    "ReceivingYards": 1174,
    "ReceivingTouchdowns": 9,
    "FantasyPoints": 171.4,
    "AverageDraftPosition": 25.7,
    "Rank": 9
  },
  {
    "Name": "Doug Baldwin",
    "Team": "SEA",
    "Position": "WR",
    "ByeWeek": 7,
    "Age": 29,
    "RushingYards": 6,
    "RushingTouchdowns": 0,
    "Receptions": 87,
    "ReceivingYards": 1027,
    "ReceivingTouchdowns": 8,
    "FantasyPoints": 151.3,
    "AverageDraftPosition": 29.6,
    "Rank": 10
  },
  {
    "Name": "T.Y. Hilton",
    "Team": "IND",
    "Position": "WR",
    "ByeWeek": 9,
    "Age": 28,
    "RushingYards": 0,
    "RushingTouchdowns": 0,
    "Receptions": 77,
    "ReceivingYards": 1211,
    "ReceivingTouchdowns": 7,
    "FantasyPoints": 161.1,
    "AverageDraftPosition": 29.9,
    "Rank": 11
  },
  {
    "Name": "Tyreek Hill",
    "Team": "KC",
    "Position": "WR",
    "ByeWeek": 12,
    "Age": 24,
    "RushingYards": 101,
    "RushingTouchdowns": 1,
    "Receptions": 73,
    "ReceivingYards": 1088,
    "ReceivingTouchdowns": 6,
    "FantasyPoints": 160.9,
    "AverageDraftPosition": 30.2,
    "Rank": 12
  },
  {
    "Name": "Adam Thielen",
    "Team": "MIN",
    "Position": "WR",
    "ByeWeek": 10,
    "Age": 27,
    "RushingYards": 4,
    "RushingTouchdowns": 0,
    "Receptions": 87,
    "ReceivingYards": 1163,
    "ReceivingTouchdowns": 6,
    "FantasyPoints": 150.7,
    "AverageDraftPosition": 34.5,
    "Rank": 13
  },
  {
    "Name": "Stefon Diggs",
    "Team": "MIN",
    "Position": "WR",
    "ByeWeek": 10,
    "Age": 24,
    "RushingYards": 20,
    "RushingTouchdowns": 0,
    "Receptions": 77,
    "ReceivingYards": 1033,
    "ReceivingTouchdowns": 8,
    "FantasyPoints": 153.3,
    "AverageDraftPosition": 34.7,
    "Rank": 14
  },
  {
    "Name": "Amari Cooper",
    "Team": "OAK",
    "Position": "WR",
    "ByeWeek": 7,
    "Age": 24,
    "RushingYards": 5,
    "RushingTouchdowns": 0,
    "Receptions": 76,
    "ReceivingYards": 1013,
    "ReceivingTouchdowns": 7,
    "FantasyPoints": 143.8,
    "AverageDraftPosition": 37.8,
    "Rank": 15
  },
  {
    "Name": "Josh Gordon",
    "Team": "CLE",
    "Position": "WR",
    "ByeWeek": 11,
    "Age": 27,
    "RushingYards": 4,
    "RushingTouchdowns": 0,
    "Receptions": 68,
    "ReceivingYards": 964,
    "ReceivingTouchdowns": 7,
    "FantasyPoints": 138.8,
    "AverageDraftPosition": 42.5,
    "Rank": 16
  },
  {
    "Name": "Brandin Cooks",
    "Team": "LAR",
    "Position": "WR",
    "ByeWeek": 12,
    "Age": 24,
    "RushingYards": 38,
    "RushingTouchdowns": 0,
    "Receptions": 59,
    "ReceivingYards": 921,
    "ReceivingTouchdowns": 6,
    "FantasyPoints": 131.9,
    "AverageDraftPosition": 43.1,
    "Rank": 17
  },
  {
    "Name": "Juju Smith-Schuster",
    "Team": "PIT",
    "Position": "WR",
    "ByeWeek": 7,
    "Age": 21,
    "RushingYards": 1,
    "RushingTouchdowns": 0,
    "Receptions": 66,
    "ReceivingYards": 993,
    "ReceivingTouchdowns": 8,
    "FantasyPoints": 147.4,
    "AverageDraftPosition": 44.7,
    "Rank": 18
  },
  {
    "Name": "Demaryius Thomas",
    "Team": "DEN",
    "Position": "WR",
    "ByeWeek": 10,
    "Age": 30,
    "RushingYards": 0,
    "RushingTouchdowns": 0,
    "Receptions": 84,
    "ReceivingYards": 966,
    "ReceivingTouchdowns": 6,
    "FantasyPoints": 130.6,
    "AverageDraftPosition": 46.5,
    "Rank": 19
  },
  {
    "Name": "Alshon Jeffery",
    "Team": "PHI",
    "Position": "WR",
    "ByeWeek": 9,
    "Age": 28,
    "RushingYards": 0,
    "RushingTouchdowns": 0,
    "Receptions": 71,
    "ReceivingYards": 930,
    "ReceivingTouchdowns": 8,
    "FantasyPoints": 141,
    "AverageDraftPosition": 48.4,
    "Rank": 20
  },
  {
    "Name": "Larry Fitzgerald",
    "Team": "ARI",
    "Position": "WR",
    "ByeWeek": 9,
    "Age": 34,
    "RushingYards": 0,
    "RushingTouchdowns": 0,
    "Receptions": 94,
    "ReceivingYards": 980,
    "ReceivingTouchdowns": 7,
    "FantasyPoints": 138,
    "AverageDraftPosition": 49.8,
    "Rank": 21
  },
  {
    "Name": "Allen Robinson",
    "Team": "CHI",
    "Position": "WR",
    "ByeWeek": 5,
    "Age": 24,
    "RushingYards": 0,
    "RushingTouchdowns": 0,
    "Receptions": 72,
    "ReceivingYards": 1007,
    "ReceivingTouchdowns": 7,
    "FantasyPoints": 142.7,
    "AverageDraftPosition": 51.8,
    "Rank": 22
  },
  {
    "Name": "Marvin Jones",
    "Team": "DET",
    "Position": "WR",
    "ByeWeek": 6,
    "Age": 28,
    "RushingYards": 0,
    "RushingTouchdowns": 0,
    "Receptions": 69,
    "ReceivingYards": 1043,
    "ReceivingTouchdowns": 8,
    "FantasyPoints": 152.3,
    "AverageDraftPosition": 55.6,
    "Rank": 23
  },
  {
    "Name": "Chris Hogan",
    "Team": "NE",
    "Position": "WR",
    "ByeWeek": 11,
    "Age": 29,
    "RushingYards": 18,
    "RushingTouchdowns": 0,
    "Receptions": 65,
    "ReceivingYards": 855,
    "ReceivingTouchdowns": 8,
    "FantasyPoints": 135.3,
    "AverageDraftPosition": 58.6,
    "Rank": 24
  },
  {
    "Name": "Will Fuller",
    "Team": "HOU",
    "Position": "WR",
    "ByeWeek": 10,
    "Age": 24,
    "RushingYards": 14,
    "RushingTouchdowns": 0,
    "Receptions": 58,
    "ReceivingYards": 844,
    "ReceivingTouchdowns": 7,
    "FantasyPoints": 127.8,
    "AverageDraftPosition": 61.6,
    "Rank": 25
  },
  {
    "Name": "Golden Tate",
    "Team": "DET",
    "Position": "WR",
    "ByeWeek": 6,
    "Age": 30,
    "RushingYards": 19,
    "RushingTouchdowns": 0,
    "Receptions": 93,
    "ReceivingYards": 1019,
    "ReceivingTouchdowns": 6,
    "FantasyPoints": 137.8,
    "AverageDraftPosition": 63.6,
    "Rank": 26
  },
  {
    "Name": "Sammy Watkins",
    "Team": "KC",
    "Position": "WR",
    "ByeWeek": 12,
    "Age": 25,
    "RushingYards": 1,
    "RushingTouchdowns": 0,
    "Receptions": 61,
    "ReceivingYards": 896,
    "ReceivingTouchdowns": 6,
    "FantasyPoints": 125.7,
    "AverageDraftPosition": 66,
    "Rank": 27
  },
  {
    "Name": "Jarvis Landry",
    "Team": "CLE",
    "Position": "WR",
    "ByeWeek": 11,
    "Age": 25,
    "RushingYards": 4,
    "RushingTouchdowns": 0,
    "Receptions": 81,
    "ReceivingYards": 878,
    "ReceivingTouchdowns": 5,
    "FantasyPoints": 114.2,
    "AverageDraftPosition": 69.3,
    "Rank": 28
  },
  {
    "Name": "Corey Davis",
    "Team": "TEN",
    "Position": "WR",
    "ByeWeek": 8,
    "Age": 23,
    "RushingYards": 0,
    "RushingTouchdowns": 0,
    "Receptions": 71,
    "ReceivingYards": 929,
    "ReceivingTouchdowns": 6,
    "FantasyPoints": 126.9,
    "AverageDraftPosition": 71,
    "Rank": 29
  },
  {
    "Name": "Michael Crabtree",
    "Team": "BAL",
    "Position": "WR",
    "ByeWeek": 10,
    "Age": 30,
    "RushingYards": 1,
    "RushingTouchdowns": 0,
    "Receptions": 74,
    "ReceivingYards": 798,
    "ReceivingTouchdowns": 7,
    "FantasyPoints": 121.9,
    "AverageDraftPosition": 74.8,
    "Rank": 30
  },
  {
    "Name": "Jordy Nelson",
    "Team": "OAK",
    "Position": "WR",
    "ByeWeek": 7,
    "Age": 33,
    "RushingYards": 6,
    "RushingTouchdowns": 0,
    "Receptions": 72,
    "ReceivingYards": 756,
    "ReceivingTouchdowns": 6,
    "FantasyPoints": 112.2,
    "AverageDraftPosition": 78.8,
    "Rank": 31
  },
  {
    "Name": "Emmanuel Sanders",
    "Team": "DEN",
    "Position": "WR",
    "ByeWeek": 10,
    "Age": 31,
    "RushingYards": 1,
    "RushingTouchdowns": 0,
    "Receptions": 70,
    "ReceivingYards": 947,
    "ReceivingTouchdowns": 6,
    "FantasyPoints": 130.8,
    "AverageDraftPosition": 79.5,
    "Rank": 32
  },
  {
    "Name": "Julian Edelman",
    "Team": "NE",
    "Position": "WR",
    "ByeWeek": 11,
    "Age": 32,
    "RushingYards": 24,
    "RushingTouchdowns": 0,
    "Receptions": 75,
    "ReceivingYards": 846,
    "ReceivingTouchdowns": 6,
    "FantasyPoints": 121,
    "AverageDraftPosition": 81.4,
    "Rank": 33
  },
  {
    "Name": "Marquise Goodwin",
    "Team": "SF",
    "Position": "WR",
    "ByeWeek": 11,
    "Age": 27,
    "RushingYards": 25,
    "RushingTouchdowns": 0,
    "Receptions": 57,
    "ReceivingYards": 907,
    "ReceivingTouchdowns": 5,
    "FantasyPoints": 123.2,
    "AverageDraftPosition": 83.1,
    "Rank": 34
  },
  {
    "Name": "Devin Funchess",
    "Team": "CAR",
    "Position": "WR",
    "ByeWeek": 4,
    "Age": 24,
    "RushingYards": 1,
    "RushingTouchdowns": 0,
    "Receptions": 64,
    "ReceivingYards": 821,
    "ReceivingTouchdowns": 6,
    "FantasyPoints": 118.2,
    "AverageDraftPosition": 85.3,
    "Rank": 35
  },
  {
    "Name": "Randall Cobb",
    "Team": "GB",
    "Position": "WR",
    "ByeWeek": 7,
    "Age": 27,
    "RushingYards": 45,
    "RushingTouchdowns": 0,
    "Receptions": 76,
    "ReceivingYards": 769,
    "ReceivingTouchdowns": 5,
    "FantasyPoints": 111.4,
    "AverageDraftPosition": 91.2,
    "Rank": 36
  },
  {
    "Name": "Robert Woods",
    "Team": "LAR",
    "Position": "WR",
    "ByeWeek": 12,
    "Age": 26,
    "RushingYards": 13,
    "RushingTouchdowns": 0,
    "Receptions": 66,
    "ReceivingYards": 895,
    "ReceivingTouchdowns": 6,
    "FantasyPoints": 124.8,
    "AverageDraftPosition": 96.3,
    "Rank": 37
  },
  {
    "Name": "Robby Anderson",
    "Team": "NYJ",
    "Position": "WR",
    "ByeWeek": 11,
    "Age": 25,
    "RushingYards": 21,
    "RushingTouchdowns": 0,
    "Receptions": 61,
    "ReceivingYards": 880,
    "ReceivingTouchdowns": 6,
    "FantasyPoints": 126.1,
    "AverageDraftPosition": 98,
    "Rank": 38
  },
  {
    "Name": "Allen Hurns",
    "Team": "DAL",
    "Position": "WR",
    "ByeWeek": 8,
    "Age": 26,
    "RushingYards": 0,
    "RushingTouchdowns": 0,
    "Receptions": 56,
    "ReceivingYards": 707,
    "ReceivingTouchdowns": 5,
    "FantasyPoints": 100.7,
    "AverageDraftPosition": 101.8,
    "Rank": 39
  },
  {
    "Name": "Devante Parker",
    "Team": "MIA",
    "Position": "WR",
    "ByeWeek": 11,
    "Age": 25,
    "RushingYards": 0,
    "RushingTouchdowns": 0,
    "Receptions": 64,
    "ReceivingYards": 834,
    "ReceivingTouchdowns": 5,
    "FantasyPoints": 113.4,
    "AverageDraftPosition": 103.4,
    "Rank": 40
  },
  {
    "Name": "Pierre Garcon",
    "Team": "SF",
    "Position": "WR",
    "ByeWeek": 11,
    "Age": 31,
    "RushingYards": 2,
    "RushingTouchdowns": 0,
    "Receptions": 72,
    "ReceivingYards": 827,
    "ReceivingTouchdowns": 5,
    "FantasyPoints": 112.9,
    "AverageDraftPosition": 103.9,
    "Rank": 41
  },
  {
    "Name": "Jamison Crowder",
    "Team": "WAS",
    "Position": "WR",
    "ByeWeek": 4,
    "Age": 25,
    "RushingYards": 30,
    "RushingTouchdowns": 0,
    "Receptions": 74,
    "ReceivingYards": 876,
    "ReceivingTouchdowns": 4,
    "FantasyPoints": 110.6,
    "AverageDraftPosition": 106.4,
    "Rank": 42
  },
  {
    "Name": "Cooper Kupp",
    "Team": "LAR",
    "Position": "WR",
    "ByeWeek": 12,
    "Age": 25,
    "RushingYards": 1,
    "RushingTouchdowns": 0,
    "Receptions": 68,
    "ReceivingYards": 902,
    "ReceivingTouchdowns": 6,
    "FantasyPoints": 124.3,
    "AverageDraftPosition": 109.7,
    "Rank": 43
  },
  {
    "Name": "Kelvin Benjamin",
    "Team": "BUF",
    "Position": "WR",
    "ByeWeek": 11,
    "Age": 27,
    "RushingYards": 0,
    "RushingTouchdowns": 0,
    "Receptions": 60,
    "ReceivingYards": 813,
    "ReceivingTouchdowns": 5,
    "FantasyPoints": 111.3,
    "AverageDraftPosition": 111.5,
    "Rank": 44
  },
  {
    "Name": "Calvin Ridley",
    "Team": "ATL",
    "Position": "WR",
    "ByeWeek": 8,
    "Age": 23,
    "RushingYards": 13,
    "RushingTouchdowns": 0,
    "Receptions": 55,
    "ReceivingYards": 666,
    "ReceivingTouchdowns": 4,
    "FantasyPoints": 91.9,
    "AverageDraftPosition": 114.7,
    "Rank": 45
  },
  {
    "Name": "Nelson Agholor",
    "Team": "PHI",
    "Position": "WR",
    "ByeWeek": 9,
    "Age": 25,
    "RushingYards": 39,
    "RushingTouchdowns": 0,
    "Receptions": 63,
    "ReceivingYards": 832,
    "ReceivingTouchdowns": 6,
    "FantasyPoints": 123.1,
    "AverageDraftPosition": 117.5,
    "Rank": 46
  },
  {
    "Name": "D.J. Moore",
    "Team": "CAR",
    "Position": "WR",
    "ByeWeek": 4,
    "Age": 21,
    "RushingYards": 20,
    "RushingTouchdowns": 0,
    "Receptions": 52,
    "ReceivingYards": 682,
    "ReceivingTouchdowns": 5,
    "FantasyPoints": 100.2,
    "AverageDraftPosition": 123.3,
    "Rank": 47
  },
  {
    "Name": "Mike Williams",
    "Team": "LAC",
    "Position": "WR",
    "ByeWeek": 8,
    "Age": 23,
    "RushingYards": 2,
    "RushingTouchdowns": 0,
    "Receptions": 50,
    "ReceivingYards": 600,
    "ReceivingTouchdowns": 4,
    "FantasyPoints": 84.2,
    "AverageDraftPosition": 123.9,
    "Rank": 48
  },
  {
    "Name": "Sterling Shepard",
    "Team": "NYG",
    "Position": "WR",
    "ByeWeek": 9,
    "Age": 24,
    "RushingYards": 19,
    "RushingTouchdowns": 0,
    "Receptions": 68,
    "ReceivingYards": 840,
    "ReceivingTouchdowns": 5,
    "FantasyPoints": 115.9,
    "AverageDraftPosition": 127,
    "Rank": 49
  },
  {
    "Name": "Cameron Meredith",
    "Team": "NO",
    "Position": "WR",
    "ByeWeek": 6,
    "Age": 25,
    "RushingYards": 0,
    "RushingTouchdowns": 0,
    "Receptions": 54,
    "ReceivingYards": 690,
    "ReceivingTouchdowns": 5,
    "FantasyPoints": 97,
    "AverageDraftPosition": 129.3,
    "Rank": 50
  },
  {
    "Name": "Martavis Bryant",
    "Team": "OAK",
    "Position": "WR",
    "ByeWeek": 7,
    "Age": 26,
    "RushingYards": 18,
    "RushingTouchdowns": 0,
    "Receptions": 43,
    "ReceivingYards": 626,
    "ReceivingTouchdowns": 4,
    "FantasyPoints": 88.4,
    "AverageDraftPosition": 129.7,
    "Rank": 51
  },
  {
    "Name": "Kenny Golladay",
    "Team": "DET",
    "Position": "WR",
    "ByeWeek": 6,
    "Age": 24,
    "RushingYards": 5,
    "RushingTouchdowns": 0,
    "Receptions": 52,
    "ReceivingYards": 725,
    "ReceivingTouchdowns": 5,
    "FantasyPoints": 103,
    "AverageDraftPosition": 134.4,
    "Rank": 52
  },
  {
    "Name": "Marqise Lee",
    "Team": "JAX",
    "Position": "WR",
    "ByeWeek": 9,
    "Age": 26,
    "RushingYards": 17,
    "RushingTouchdowns": 0,
    "Receptions": 67,
    "ReceivingYards": 836,
    "ReceivingTouchdowns": 5,
    "FantasyPoints": 115.3,
    "AverageDraftPosition": 135.5,
    "Rank": 53
  },
  {
    "Name": "Kenny Stills",
    "Team": "MIA",
    "Position": "WR",
    "ByeWeek": 11,
    "Age": 26,
    "RushingYards": 0,
    "RushingTouchdowns": 0,
    "Receptions": 61,
    "ReceivingYards": 834,
    "ReceivingTouchdowns": 5,
    "FantasyPoints": 111.4,
    "AverageDraftPosition": 137.3,
    "Rank": 54
  },
  {
    "Name": "Josh Doctson",
    "Team": "WAS",
    "Position": "WR",
    "ByeWeek": 4,
    "Age": 25,
    "RushingYards": 2,
    "RushingTouchdowns": 0,
    "Receptions": 56,
    "ReceivingYards": 802,
    "ReceivingTouchdowns": 6,
    "FantasyPoints": 116.4,
    "AverageDraftPosition": 141.2,
    "Rank": 55
  },
  {
    "Name": "Geronimo Allison",
    "Team": "GB",
    "Position": "WR",
    "ByeWeek": 7,
    "Age": 24,
    "RushingYards": 5,
    "RushingTouchdowns": 0,
    "Receptions": 44,
    "ReceivingYards": 550,
    "ReceivingTouchdowns": 4,
    "FantasyPoints": 77.5,
    "AverageDraftPosition": 146.3,
    "Rank": 56
  },
  {
    "Name": "Rishard Matthews",
    "Team": "TEN",
    "Position": "WR",
    "ByeWeek": 8,
    "Age": 28,
    "RushingYards": 0,
    "RushingTouchdowns": 0,
    "Receptions": 62,
    "ReceivingYards": 794,
    "ReceivingTouchdowns": 5,
    "FantasyPoints": 109.4,
    "AverageDraftPosition": 154.2,
    "Rank": 57
  },
  {
    "Name": "Tyler Lockett",
    "Team": "SEA",
    "Position": "WR",
    "ByeWeek": 7,
    "Age": 24,
    "RushingYards": 59,
    "RushingTouchdowns": 0,
    "Receptions": 56,
    "ReceivingYards": 692,
    "ReceivingTouchdowns": 5,
    "FantasyPoints": 105.1,
    "AverageDraftPosition": 154.5,
    "Rank": 58
  },
  {
    "Name": "Michael Gallup",
    "Team": "DAL",
    "Position": "WR",
    "ByeWeek": 8,
    "Age": 22,
    "RushingYards": 11,
    "RushingTouchdowns": 0,
    "Receptions": 51,
    "ReceivingYards": 571,
    "ReceivingTouchdowns": 4,
    "FantasyPoints": 82.2,
    "AverageDraftPosition": 156.2,
    "Rank": 59
  },
  {
    "Name": "Anthony Miller",
    "Team": "CHI",
    "Position": "WR",
    "ByeWeek": 5,
    "Age": 23,
    "RushingYards": 8,
    "RushingTouchdowns": 0,
    "Receptions": 50,
    "ReceivingYards": 663,
    "ReceivingTouchdowns": 4,
    "FantasyPoints": 91.1,
    "AverageDraftPosition": 158.3,
    "Rank": 60
  },
  {
    "Name": "Tyrell Williams",
    "Team": "LAC",
    "Position": "WR",
    "ByeWeek": 8,
    "Age": 26,
    "RushingYards": 0,
    "RushingTouchdowns": 0,
    "Receptions": 42,
    "ReceivingYards": 664,
    "ReceivingTouchdowns": 4,
    "FantasyPoints": 88.4,
    "AverageDraftPosition": 160.2,
    "Rank": 61
  },
  {
    "Name": "Dede Westbrook",
    "Team": "JAX",
    "Position": "WR",
    "ByeWeek": 9,
    "Age": 24,
    "RushingYards": 1,
    "RushingTouchdowns": 0,
    "Receptions": 55,
    "ReceivingYards": 677,
    "ReceivingTouchdowns": 4,
    "FantasyPoints": 91.8,
    "AverageDraftPosition": 161.4,
    "Rank": 62
  },
  {
    "Name": "Ted Ginn",
    "Team": "NO",
    "Position": "WR",
    "ByeWeek": 6,
    "Age": 33,
    "RushingYards": 46,
    "RushingTouchdowns": 0,
    "Receptions": 45,
    "ReceivingYards": 699,
    "ReceivingTouchdowns": 5,
    "FantasyPoints": 104.5,
    "AverageDraftPosition": 164.6,
    "Rank": 63
  },
  {
    "Name": "DeSean Jackson",
    "Team": "TB",
    "Position": "WR",
    "ByeWeek": 5,
    "Age": 31,
    "RushingYards": 25,
    "RushingTouchdowns": 0,
    "Receptions": 55,
    "ReceivingYards": 803,
    "ReceivingTouchdowns": 4,
    "FantasyPoints": 106.8,
    "AverageDraftPosition": 165.2,
    "Rank": 64
  },
  {
    "Name": "Brandon Marshall",
    "Team": "SEA",
    "Position": "WR",
    "ByeWeek": 7,
    "Age": 34,
    "RushingYards": 0,
    "RushingTouchdowns": 0,
    "Receptions": 40,
    "ReceivingYards": 472,
    "ReceivingTouchdowns": 4,
    "FantasyPoints": 71.2,
    "AverageDraftPosition": 165.7,
    "Rank": 65
  },
  {
    "Name": "Quincy Enunwa",
    "Team": "NYJ",
    "Position": "WR",
    "ByeWeek": 11,
    "Age": 26,
    "RushingYards": 3,
    "RushingTouchdowns": 0,
    "Receptions": 36,
    "ReceivingYards": 480,
    "ReceivingTouchdowns": 3,
    "FantasyPoints": 66.3,
    "AverageDraftPosition": 166.2,
    "Rank": 66
  },
  {
    "Name": "Christian Kirk",
    "Team": "ARI",
    "Position": "WR",
    "ByeWeek": 9,
    "Age": 21,
    "RushingYards": 6,
    "RushingTouchdowns": 0,
    "Receptions": 32,
    "ReceivingYards": 429,
    "ReceivingTouchdowns": 3,
    "FantasyPoints": 61.5,
    "AverageDraftPosition": 168.7,
    "Rank": 67
  },
  {
    "Name": "Mohamed Sanu",
    "Team": "ATL",
    "Position": "WR",
    "ByeWeek": 8,
    "Age": 28,
    "RushingYards": 13,
    "RushingTouchdowns": 0,
    "Receptions": 61,
    "ReceivingYards": 662,
    "ReceivingTouchdowns": 4,
    "FantasyPoints": 91.5,
    "AverageDraftPosition": 169.3,
    "Rank": 68
  },
  {
    "Name": "Paul Richardson",
    "Team": "WAS",
    "Position": "WR",
    "ByeWeek": 4,
    "Age": 26,
    "RushingYards": 1,
    "RushingTouchdowns": 0,
    "Receptions": 55,
    "ReceivingYards": 729,
    "ReceivingTouchdowns": 4,
    "FantasyPoints": 97,
    "AverageDraftPosition": 169.4,
    "Rank": 69
  },
  {
    "Name": "Terrance Williams",
    "Team": "DAL",
    "Position": "WR",
    "ByeWeek": 8,
    "Age": 28,
    "RushingYards": 9,
    "RushingTouchdowns": 0,
    "Receptions": 51,
    "ReceivingYards": 623,
    "ReceivingTouchdowns": 4,
    "FantasyPoints": 87.2,
    "AverageDraftPosition": 178,
    "Rank": 70
  },
  {
    "Name": "Mike Wallace",
    "Team": "PHI",
    "Position": "WR",
    "ByeWeek": 9,
    "Age": 32,
    "RushingYards": 1,
    "RushingTouchdowns": 0,
    "Receptions": 41,
    "ReceivingYards": 603,
    "ReceivingTouchdowns": 3,
    "FantasyPoints": 78.4,
    "AverageDraftPosition": 180,
    "Rank": 71
  },
  {
    "Name": "Ryan Grant",
    "Team": "IND",
    "Position": "WR",
    "ByeWeek": 9,
    "Age": 27,
    "RushingYards": 0,
    "RushingTouchdowns": 0,
    "Receptions": 56,
    "ReceivingYards": 630,
    "ReceivingTouchdowns": 4,
    "FantasyPoints": 87,
    "AverageDraftPosition": 181,
    "Rank": 72
  },
  {
    "Name": "Albert Wilson",
    "Team": "MIA",
    "Position": "WR",
    "ByeWeek": 11,
    "Age": 26,
    "RushingYards": 13,
    "RushingTouchdowns": 0,
    "Receptions": 45,
    "ReceivingYards": 547,
    "ReceivingTouchdowns": 3,
    "FantasyPoints": 74,
    "AverageDraftPosition": 182,
    "Rank": 73
  },
  {
    "Name": "Zay Jones",
    "Team": "BUF",
    "Position": "WR",
    "ByeWeek": 11,
    "Age": 23,
    "RushingYards": 1,
    "RushingTouchdowns": 0,
    "Receptions": 47,
    "ReceivingYards": 492,
    "ReceivingTouchdowns": 3,
    "FantasyPoints": 67.3,
    "AverageDraftPosition": 184,
    "Rank": 74
  },
  {
    "Name": "Willie Snead",
    "Team": "BAL",
    "Position": "WR",
    "ByeWeek": 10,
    "Age": 25,
    "RushingYards": 0,
    "RushingTouchdowns": 0,
    "Receptions": 50,
    "ReceivingYards": 514,
    "ReceivingTouchdowns": 2,
    "FantasyPoints": 63.4,
    "AverageDraftPosition": 189,
    "Rank": 75
  },
  {
    "Name": "John Brown",
    "Team": "BAL",
    "Position": "WR",
    "ByeWeek": 10,
    "Age": 28,
    "RushingYards": 7,
    "RushingTouchdowns": 0,
    "Receptions": 43,
    "ReceivingYards": 606,
    "ReceivingTouchdowns": 4,
    "FantasyPoints": 85.3,
    "AverageDraftPosition": 193,
    "Rank": 76
  },
  {
    "Name": "Travis Benjamin",
    "Team": "LAC",
    "Position": "WR",
    "ByeWeek": 8,
    "Age": 28,
    "RushingYards": 60,
    "RushingTouchdowns": 0,
    "Receptions": 30,
    "ReceivingYards": 477,
    "ReceivingTouchdowns": 3,
    "FantasyPoints": 71.7,
    "AverageDraftPosition": 195,
    "Rank": 77
  },
  {
    "Name": "Tre'Quan Smith",
    "Team": "NO",
    "Position": "WR",
    "ByeWeek": 6,
    "Age": 22,
    "RushingYards": 0,
    "RushingTouchdowns": 0,
    "Receptions": 19,
    "ReceivingYards": 317,
    "ReceivingTouchdowns": 2,
    "FantasyPoints": 41.7,
    "AverageDraftPosition": 197,
    "Rank": 78
  },
  {
    "Name": "Donte Moncrief",
    "Team": "JAX",
    "Position": "WR",
    "ByeWeek": 9,
    "Age": 24,
    "RushingYards": 0,
    "RushingTouchdowns": 0,
    "Receptions": 39,
    "ReceivingYards": 513,
    "ReceivingTouchdowns": 3,
    "FantasyPoints": 69.3,
    "AverageDraftPosition": 198,
    "Rank": 79
  },
  {
    "Name": "Kendall Wright",
    "Team": "MIN",
    "Position": "WR",
    "ByeWeek": 10,
    "Age": 28,
    "RushingYards": 0,
    "RushingTouchdowns": 0,
    "Receptions": 42,
    "ReceivingYards": 444,
    "ReceivingTouchdowns": 3,
    "FantasyPoints": 62.4,
    "AverageDraftPosition": 201,
    "Rank": 80
  },
  {
    "Name": "Terrelle Pryor",
    "Team": "NYJ",
    "Position": "WR",
    "ByeWeek": 11,
    "Age": 29,
    "RushingYards": 13,
    "RushingTouchdowns": 0,
    "Receptions": 35,
    "ReceivingYards": 453,
    "ReceivingTouchdowns": 3,
    "FantasyPoints": 64.6,
    "AverageDraftPosition": 202,
    "Rank": 81
  },
  {
    "Name": "Jermaine Kearse",
    "Team": "NYJ",
    "Position": "WR",
    "ByeWeek": 11,
    "Age": 28,
    "RushingYards": 0,
    "RushingTouchdowns": 0,
    "Receptions": 39,
    "ReceivingYards": 498,
    "ReceivingTouchdowns": 3,
    "FantasyPoints": 67.8,
    "AverageDraftPosition": 203,
    "Rank": 82
  },
  {
    "Name": "Danny Amendola",
    "Team": "MIA",
    "Position": "WR",
    "ByeWeek": 11,
    "Age": 32,
    "RushingYards": 5,
    "RushingTouchdowns": 0,
    "Receptions": 56,
    "ReceivingYards": 602,
    "ReceivingTouchdowns": 4,
    "FantasyPoints": 84.7,
    "AverageDraftPosition": 206,
    "Rank": 83
  },
  {
    "Name": "John Ross",
    "Team": "CIN",
    "Position": "WR",
    "ByeWeek": 9,
    "Age": 23,
    "RushingYards": 29,
    "RushingTouchdowns": 0,
    "Receptions": 35,
    "ReceivingYards": 535,
    "ReceivingTouchdowns": 3,
    "FantasyPoints": 74.4,
    "AverageDraftPosition": 207,
    "Rank": 84
  },
  {
    "Name": "JJ Nelson",
    "Team": "ARI",
    "Position": "WR",
    "ByeWeek": 9,
    "Age": 24,
    "RushingYards": 16,
    "RushingTouchdowns": 0,
    "Receptions": 29,
    "ReceivingYards": 452,
    "ReceivingTouchdowns": 3,
    "FantasyPoints": 62.8,
    "AverageDraftPosition": 208,
    "Rank": 85
  },
  {
    "Name": "Taywan Taylor",
    "Team": "TEN",
    "Position": "WR",
    "ByeWeek": 8,
    "Age": 23,
    "RushingYards": 32,
    "RushingTouchdowns": 0,
    "Receptions": 42,
    "ReceivingYards": 574,
    "ReceivingTouchdowns": 3,
    "FantasyPoints": 78.6,
    "AverageDraftPosition": 211,
    "Rank": 86
  },
  {
    "Name": "Seth Roberts",
    "Team": "OAK",
    "Position": "WR",
    "ByeWeek": 7,
    "Age": 27,
    "RushingYards": 12,
    "RushingTouchdowns": 1,
    "Receptions": 35,
    "ReceivingYards": 368,
    "ReceivingTouchdowns": 2,
    "FantasyPoints": 54,
    "AverageDraftPosition": 212,
    "Rank": 87
  },
  {
    "Name": "Cole Beasley",
    "Team": "DAL",
    "Position": "WR",
    "ByeWeek": 8,
    "Age": 29,
    "RushingYards": 1,
    "RushingTouchdowns": 0,
    "Receptions": 57,
    "ReceivingYards": 543,
    "ReceivingTouchdowns": 3,
    "FantasyPoints": 72.4,
    "AverageDraftPosition": 214,
    "Rank": 88
  },
  {
    "Name": "Bennie Fowler",
    "Team": "CHI",
    "Position": "WR",
    "ByeWeek": 5,
    "Age": 27,
    "RushingYards": 0,
    "RushingTouchdowns": 0,
    "Receptions": 23,
    "ReceivingYards": 199,
    "ReceivingTouchdowns": 1,
    "FantasyPoints": 25.9,
    "AverageDraftPosition": 215,
    "Rank": 89
  },
  {
    "Name": "Chris Godwin",
    "Team": "TB",
    "Position": "WR",
    "ByeWeek": 5,
    "Age": 22,
    "RushingYards": 1,
    "RushingTouchdowns": 0,
    "Receptions": 35,
    "ReceivingYards": 522,
    "ReceivingTouchdowns": 3,
    "FantasyPoints": 70.3,
    "AverageDraftPosition": 217,
    "Rank": 90
  },
  {
    "Name": "James Washington",
    "Team": "PIT",
    "Position": "WR",
    "ByeWeek": 7,
    "Age": 22,
    "RushingYards": 10,
    "RushingTouchdowns": 0,
    "Receptions": 42,
    "ReceivingYards": 668,
    "ReceivingTouchdowns": 4,
    "FantasyPoints": 91.8,
    "AverageDraftPosition": 219,
    "Rank": 91
  },
  {
    "Name": "Courtland Sutton",
    "Team": "DEN",
    "Position": "WR",
    "ByeWeek": 10,
    "Age": 22,
    "RushingYards": 4,
    "RushingTouchdowns": 0,
    "Receptions": 33,
    "ReceivingYards": 450,
    "ReceivingTouchdowns": 4,
    "FantasyPoints": 69.4,
    "AverageDraftPosition": 220,
    "Rank": 92
  },
  {
    "Name": "Taylor Gabriel",
    "Team": "CHI",
    "Position": "WR",
    "ByeWeek": 5,
    "Age": 27,
    "RushingYards": 22,
    "RushingTouchdowns": 0,
    "Receptions": 31,
    "ReceivingYards": 413,
    "ReceivingTouchdowns": 2,
    "FantasyPoints": 55.5,
    "AverageDraftPosition": 221,
    "Rank": 93
  },
  {
    "Name": "Chester Rogers",
    "Team": "IND",
    "Position": "WR",
    "ByeWeek": 9,
    "Age": 24,
    "RushingYards": 14,
    "RushingTouchdowns": 0,
    "Receptions": 31,
    "ReceivingYards": 430,
    "ReceivingTouchdowns": 2,
    "FantasyPoints": 56.4,
    "AverageDraftPosition": 222,
    "Rank": 94
  },
  {
    "Name": "Trent Taylor",
    "Team": "SF",
    "Position": "WR",
    "ByeWeek": 11,
    "Age": 24,
    "RushingYards": 0,
    "RushingTouchdowns": 0,
    "Receptions": 35,
    "ReceivingYards": 377,
    "ReceivingTouchdowns": 2,
    "FantasyPoints": 47.7,
    "AverageDraftPosition": 223,
    "Rank": 95
  },
  {
    "Name": "Adam Humphries",
    "Team": "TB",
    "Position": "WR",
    "ByeWeek": 5,
    "Age": 25,
    "RushingYards": 8,
    "RushingTouchdowns": 0,
    "Receptions": 50,
    "ReceivingYards": 550,
    "ReceivingTouchdowns": 2,
    "FantasyPoints": 67.8,
    "AverageDraftPosition": 224,
    "Rank": 96
  },
  {
    "Name": "Curtis Samuel",
    "Team": "CAR",
    "Position": "WR",
    "ByeWeek": 4,
    "Age": 21,
    "RushingYards": 50,
    "RushingTouchdowns": 0,
    "Receptions": 14,
    "ReceivingYards": 166,
    "ReceivingTouchdowns": 1,
    "FantasyPoints": 27.6,
    "AverageDraftPosition": 230,
    "Rank": 97
  },
  {
    "Name": "Antonio Callaway",
    "Team": "CLE",
    "Position": "WR",
    "ByeWeek": 11,
    "Age": 21,
    "RushingYards": 5,
    "RushingTouchdowns": 0,
    "Receptions": 17,
    "ReceivingYards": 253,
    "ReceivingTouchdowns": 1,
    "FantasyPoints": 31.8,
    "AverageDraftPosition": 234,
    "Rank": 98
  },
  {
    "Name": "Keke Coutee",
    "Team": "HOU",
    "Position": "WR",
    "ByeWeek": 10,
    "Age": 21,
    "RushingYards": 0,
    "RushingTouchdowns": 0,
    "Receptions": 31,
    "ReceivingYards": 407,
    "ReceivingTouchdowns": 3,
    "FantasyPoints": 58.7,
    "AverageDraftPosition": 237,
    "Rank": 99
  },
  {
    "Name": "D.J. Chark",
    "Team": "JAX",
    "Position": "WR",
    "ByeWeek": 9,
    "Age": 21,
    "RushingYards": 0,
    "RushingTouchdowns": 0,
    "Receptions": 15,
    "ReceivingYards": 202,
    "ReceivingTouchdowns": 1,
    "FantasyPoints": 24.2,
    "AverageDraftPosition": 238,
    "Rank": 100
  },
  {
    "Name": "Corey Coleman",
    "Team": "CLE",
    "Position": "WR",
    "ByeWeek": 11,
    "Age": 24,
    "RushingYards": 1,
    "RushingTouchdowns": 0,
    "Receptions": 42,
    "ReceivingYards": 587,
    "ReceivingTouchdowns": 3,
    "FantasyPoints": 76.8,
    "AverageDraftPosition": 241,
    "Rank": 101
  },
  {
    "Name": "Josh Reynolds",
    "Team": "LAR",
    "Position": "WR",
    "ByeWeek": 12,
    "Age": 23,
    "RushingYards": 11,
    "RushingTouchdowns": 0,
    "Receptions": 17,
    "ReceivingYards": 188,
    "ReceivingTouchdowns": 1,
    "FantasyPoints": 23.9,
    "AverageDraftPosition": 242,
    "Rank": 102
  },
  {
    "Name": "Braxton Miller",
    "Team": "HOU",
    "Position": "WR",
    "ByeWeek": 10,
    "Age": 25,
    "RushingYards": 8,
    "RushingTouchdowns": 0,
    "Receptions": 22,
    "ReceivingYards": 219,
    "ReceivingTouchdowns": 2,
    "FantasyPoints": 34.7,
    "AverageDraftPosition": 243,
    "Rank": 103
  },
  {
    "Name": "Carlos Henderson",
    "Team": "DEN",
    "Position": "WR",
    "ByeWeek": 10,
    "Age": 23,
    "RushingYards": 0,
    "RushingTouchdowns": 0,
    "Receptions": 14,
    "ReceivingYards": 180,
    "ReceivingTouchdowns": 1,
    "FantasyPoints": 24,
    "AverageDraftPosition": 244,
    "Rank": 104
  },
  {
    "Name": "Tavon Austin",
    "Team": "DAL",
    "Position": "WR",
    "ByeWeek": 8,
    "Age": 27,
    "RushingYards": 0,
    "RushingTouchdowns": 0,
    "Receptions": 11,
    "ReceivingYards": 83,
    "ReceivingTouchdowns": 1,
    "FantasyPoints": 8.3,
    "AverageDraftPosition": 247,
    "Rank": 105
  },
  {
    "Name": "Dante Pettis",
    "Team": "SF",
    "Position": "WR",
    "ByeWeek": 11,
    "Age": 22,
    "RushingYards": 3,
    "RushingTouchdowns": 0,
    "Receptions": 31,
    "ReceivingYards": 358,
    "ReceivingTouchdowns": 3,
    "FantasyPoints": 54.1,
    "AverageDraftPosition": 248,
    "Rank": 106
  },
  {
    "Name": "Jeremy Kerley",
    "Team": "BUF",
    "Position": "WR",
    "ByeWeek": 11,
    "Age": 29,
    "RushingYards": 0,
    "RushingTouchdowns": 0,
    "Receptions": 31,
    "ReceivingYards": 357,
    "ReceivingTouchdowns": 1,
    "FantasyPoints": 39.7,
    "AverageDraftPosition": 250,
    "Rank": 107
  },
  {
    "Name": "Jakeem Grant",
    "Team": "MIA",
    "Position": "WR",
    "ByeWeek": 11,
    "Age": 25,
    "RushingYards": 11,
    "RushingTouchdowns": 0,
    "Receptions": 15,
    "ReceivingYards": 234,
    "ReceivingTouchdowns": 1,
    "FantasyPoints": 28.5,
    "AverageDraftPosition": 251,
    "Rank": 108
  },
  {
    "Name": "Roger Lewis",
    "Team": "NYG",
    "Position": "WR",
    "ByeWeek": 9,
    "Age": 24,
    "RushingYards": 1,
    "RushingTouchdowns": 0,
    "Receptions": 21,
    "ReceivingYards": 271,
    "ReceivingTouchdowns": 1,
    "FantasyPoints": 33.2,
    "AverageDraftPosition": 252,
    "Rank": 109
  },
  {
    "Name": "Brice Butler",
    "Team": "ARI",
    "Position": "WR",
    "ByeWeek": 9,
    "Age": 28,
    "RushingYards": 1,
    "RushingTouchdowns": 0,
    "Receptions": 27,
    "ReceivingYards": 408,
    "ReceivingTouchdowns": 2,
    "FantasyPoints": 52.9,
    "AverageDraftPosition": 254,
    "Rank": 110
  },
  {
    "Name": "Amara Darboh",
    "Team": "SEA",
    "Position": "WR",
    "ByeWeek": 7,
    "Age": 24,
    "RushingYards": 0,
    "RushingTouchdowns": 0,
    "Receptions": 29,
    "ReceivingYards": 373,
    "ReceivingTouchdowns": 2,
    "FantasyPoints": 49.3,
    "AverageDraftPosition": 255,
    "Rank": 111
  },
  {
    "Name": "TJ Jones",
    "Team": "DET",
    "Position": "WR",
    "ByeWeek": 6,
    "Age": 26,
    "RushingYards": 0,
    "RushingTouchdowns": 0,
    "Receptions": 22,
    "ReceivingYards": 303,
    "ReceivingTouchdowns": 2,
    "FantasyPoints": 42.3,
    "AverageDraftPosition": 256,
    "Rank": 112
  },
  {
    "Name": "Keelan Cole",
    "Team": "JAX",
    "Position": "WR",
    "ByeWeek": 9,
    "Age": 25,
    "RushingYards": 0,
    "RushingTouchdowns": 0,
    "Receptions": 36,
    "ReceivingYards": 544,
    "ReceivingTouchdowns": 3,
    "FantasyPoints": 70.4,
    "AverageDraftPosition": 258,
    "Rank": 113
  },
  {
    "Name": "Jaron Brown",
    "Team": "SEA",
    "Position": "WR",
    "ByeWeek": 7,
    "Age": 28,
    "RushingYards": 0,
    "RushingTouchdowns": 0,
    "Receptions": 27,
    "ReceivingYards": 278,
    "ReceivingTouchdowns": 2,
    "FantasyPoints": 39.8,
    "AverageDraftPosition": 261,
    "Rank": 114
  },
  {
    "Name": "Kenny Britt",
    "Team": "NE",
    "Position": "WR",
    "ByeWeek": 11,
    "Age": 29,
    "RushingYards": 0,
    "RushingTouchdowns": 0,
    "Receptions": 29,
    "ReceivingYards": 377,
    "ReceivingTouchdowns": 3,
    "FantasyPoints": 55.7,
    "AverageDraftPosition": 268,
    "Rank": 115
  },
  {
    "Name": "Chris Conley",
    "Team": "KC",
    "Position": "WR",
    "ByeWeek": 12,
    "Age": 25,
    "RushingYards": 0,
    "RushingTouchdowns": 0,
    "Receptions": 23,
    "ReceivingYards": 313,
    "ReceivingTouchdowns": 1,
    "FantasyPoints": 37.3,
    "AverageDraftPosition": 269,
    "Rank": 116
  },
  {
    "Name": "Torrey Smith",
    "Team": "CAR",
    "Position": "WR",
    "ByeWeek": 4,
    "Age": 29,
    "RushingYards": 0,
    "RushingTouchdowns": 0,
    "Receptions": 26,
    "ReceivingYards": 329,
    "ReceivingTouchdowns": 3,
    "FantasyPoints": 50.9,
    "AverageDraftPosition": 270,
    "Rank": 117
  },
  {
    "Name": "Hunter Sharp",
    "Team": "NYG",
    "Position": "WR",
    "ByeWeek": 9,
    "Age": 24,
    "RushingYards": 1,
    "RushingTouchdowns": 0,
    "Receptions": 7,
    "ReceivingYards": 123,
    "ReceivingTouchdowns": 1,
    "FantasyPoints": 18.4,
    "AverageDraftPosition": 275,
    "Rank": 118
  },
  {
    "Name": "Tanner McEvoy",
    "Team": "SEA",
    "Position": "WR",
    "ByeWeek": 7,
    "Age": 25,
    "RushingYards": 0,
    "RushingTouchdowns": 0,
    "Receptions": 6,
    "ReceivingYards": 92,
    "ReceivingTouchdowns": 0,
    "FantasyPoints": 7.2,
    "AverageDraftPosition": 276,
    "Rank": 119
  },
  {
    "Name": "Rashard Higgins",
    "Team": "CLE",
    "Position": "WR",
    "ByeWeek": 11,
    "Age": 23,
    "RushingYards": 1,
    "RushingTouchdowns": 0,
    "Receptions": 14,
    "ReceivingYards": 194,
    "ReceivingTouchdowns": 1,
    "FantasyPoints": 25.5,
    "AverageDraftPosition": 278,
    "Rank": 120
  },
  {
    "Name": "Chris Moore",
    "Team": "BAL",
    "Position": "WR",
    "ByeWeek": 10,
    "Age": 25,
    "RushingYards": 15,
    "RushingTouchdowns": 0,
    "Receptions": 26,
    "ReceivingYards": 336,
    "ReceivingTouchdowns": 2,
    "FantasyPoints": 47.1,
    "AverageDraftPosition": 280,
    "Rank": 121
  },
  {
    "Name": "J'mon Moore",
    "Team": "GB",
    "Position": "WR",
    "ByeWeek": 7,
    "Age": 23,
    "RushingYards": 0,
    "RushingTouchdowns": 0,
    "Receptions": 15,
    "ReceivingYards": 172,
    "ReceivingTouchdowns": 1,
    "FantasyPoints": 21.2,
    "AverageDraftPosition": 281,
    "Rank": 122
  },
  {
    "Name": "Cordarrelle Patterson",
    "Team": "NE",
    "Position": "WR",
    "ByeWeek": 11,
    "Age": 27,
    "RushingYards": 75,
    "RushingTouchdowns": 0,
    "Receptions": 13,
    "ReceivingYards": 155,
    "ReceivingTouchdowns": 1,
    "FantasyPoints": 29,
    "AverageDraftPosition": 282,
    "Rank": 123
  },
  {
    "Name": "Daesean Hamilton",
    "Team": "DEN",
    "Position": "WR",
    "ByeWeek": 10,
    "Age": 23,
    "RushingYards": 3,
    "RushingTouchdowns": 0,
    "Receptions": 23,
    "ReceivingYards": 272,
    "ReceivingTouchdowns": 2,
    "FantasyPoints": 39.5,
    "AverageDraftPosition": 284,
    "Rank": 124
  },
  {
    "Name": "Jaleel Scott",
    "Team": "BAL",
    "Position": "WR",
    "ByeWeek": 10,
    "Age": 23,
    "RushingYards": 0,
    "RushingTouchdowns": 0,
    "Receptions": 10,
    "ReceivingYards": 112,
    "ReceivingTouchdowns": 1,
    "FantasyPoints": 17.2,
    "AverageDraftPosition": 289,
    "Rank": 125
  },
  {
    "Name": "Jordan Lasley",
    "Team": "BAL",
    "Position": "WR",
    "ByeWeek": 10,
    "Age": 21,
    "RushingYards": 0,
    "RushingTouchdowns": 0,
    "Receptions": 11,
    "ReceivingYards": 123,
    "ReceivingTouchdowns": 1,
    "FantasyPoints": 18.3,
    "AverageDraftPosition": 290,
    "Rank": 126
  },
  {
    "Name": "Chad Williams",
    "Team": "ARI",
    "Position": "WR",
    "ByeWeek": 9,
    "Age": 23,
    "RushingYards": 18,
    "RushingTouchdowns": 0,
    "Receptions": 18,
    "ReceivingYards": 244,
    "ReceivingTouchdowns": 2,
    "FantasyPoints": 38.2,
    "AverageDraftPosition": 296,
    "Rank": 127
  },
  {
    "Name": "Mack Hollins",
    "Team": "PHI",
    "Position": "WR",
    "ByeWeek": 9,
    "Age": 24,
    "RushingYards": 0,
    "RushingTouchdowns": 0,
    "Receptions": 28,
    "ReceivingYards": 380,
    "ReceivingTouchdowns": 2,
    "FantasyPoints": 50,
    "AverageDraftPosition": 297,
    "Rank": 128
  },
  {
    "Name": "Kendrick Bourne",
    "Team": "SF",
    "Position": "WR",
    "ByeWeek": 11,
    "Age": 23,
    "RushingYards": 1,
    "RushingTouchdowns": 0,
    "Receptions": 10,
    "ReceivingYards": 197,
    "ReceivingTouchdowns": 1,
    "FantasyPoints": 25.8,
    "AverageDraftPosition": 298,
    "Rank": 129
  },
  {
    "Name": "Cody Latimer",
    "Team": "NYG",
    "Position": "WR",
    "ByeWeek": 9,
    "Age": 25,
    "RushingYards": 0,
    "RushingTouchdowns": 0,
    "Receptions": 24,
    "ReceivingYards": 304,
    "ReceivingTouchdowns": 1,
    "FantasyPoints": 36.4,
    "AverageDraftPosition": 301,
    "Rank": 130
  },
  {
    "Name": "Kevin White",
    "Team": "CHI",
    "Position": "WR",
    "ByeWeek": 5,
    "Age": 25,
    "RushingYards": 7,
    "RushingTouchdowns": 0,
    "Receptions": 27,
    "ReceivingYards": 286,
    "ReceivingTouchdowns": 2,
    "FantasyPoints": 41.3,
    "AverageDraftPosition": 303,
    "Rank": 131
  },
  {
    "Name": "Demarcus Robinson",
    "Team": "KC",
    "Position": "WR",
    "ByeWeek": 12,
    "Age": 23,
    "RushingYards": 2,
    "RushingTouchdowns": 0,
    "Receptions": 18,
    "ReceivingYards": 179,
    "ReceivingTouchdowns": 1,
    "FantasyPoints": 24.1,
    "AverageDraftPosition": 304,
    "Rank": 132
  },
  {
    "Name": "Laquon Treadwell",
    "Team": "MIN",
    "Position": "WR",
    "ByeWeek": 10,
    "Age": 23,
    "RushingYards": 0,
    "RushingTouchdowns": 0,
    "Receptions": 19,
    "ReceivingYards": 221,
    "ReceivingTouchdowns": 1,
    "FantasyPoints": 28.1,
    "AverageDraftPosition": 307,
    "Rank": 133
  },
  {
    "Name": "Malcolm Mitchell",
    "Team": "NE",
    "Position": "WR",
    "ByeWeek": 11,
    "Age": 26,
    "RushingYards": 5,
    "RushingTouchdowns": 0,
    "Receptions": 25,
    "ReceivingYards": 316,
    "ReceivingTouchdowns": 2,
    "FantasyPoints": 44.1,
    "AverageDraftPosition": 308,
    "Rank": 134
  },
  {
    "Name": "Tyler Boyd",
    "Team": "CIN",
    "Position": "WR",
    "ByeWeek": 9,
    "Age": 23,
    "RushingYards": 7,
    "RushingTouchdowns": 0,
    "Receptions": 32,
    "ReceivingYards": 367,
    "ReceivingTouchdowns": 2,
    "FantasyPoints": 47.4,
    "AverageDraftPosition": 313,
    "Rank": 135
  },
  {
    "Name": "Johnny Holton",
    "Team": "OAK",
    "Position": "WR",
    "ByeWeek": 7,
    "Age": 26,
    "RushingYards": 0,
    "RushingTouchdowns": 0,
    "Receptions": 5,
    "ReceivingYards": 109,
    "ReceivingTouchdowns": 1,
    "FantasyPoints": 14.9,
    "AverageDraftPosition": 316,
    "Rank": 136
  },
  {
    "Name": "Marquez Valdes-Scantling",
    "Team": "GB",
    "Position": "WR",
    "ByeWeek": 7,
    "Age": 23,
    "RushingYards": 0,
    "RushingTouchdowns": 0,
    "Receptions": 5,
    "ReceivingYards": 58,
    "ReceivingTouchdowns": 1,
    "FantasyPoints": 11.8,
    "AverageDraftPosition": 318,
    "Rank": 137
  },
  {
    "Name": "Equanimeous St. Brown",
    "Team": "GB",
    "Position": "WR",
    "ByeWeek": 7,
    "Age": 21,
    "RushingYards": 5,
    "RushingTouchdowns": 0,
    "Receptions": 5,
    "ReceivingYards": 157,
    "ReceivingTouchdowns": 1,
    "FantasyPoints": 22.2,
    "AverageDraftPosition": 319,
    "Rank": 138
  },
  {
    "Name": "Ryan Switzer",
    "Team": "OAK",
    "Position": "WR",
    "ByeWeek": 7,
    "Age": 23,
    "RushingYards": 2,
    "RushingTouchdowns": 0,
    "Receptions": 7,
    "ReceivingYards": 94,
    "ReceivingTouchdowns": 0,
    "FantasyPoints": 9.6,
    "AverageDraftPosition": 322,
    "Rank": 139
  },
  {
    "Name": "Ricardo Louis",
    "Team": "CLE",
    "Position": "WR",
    "ByeWeek": 11,
    "Age": 24,
    "RushingYards": 0,
    "RushingTouchdowns": 0,
    "Receptions": 3,
    "ReceivingYards": 36,
    "ReceivingTouchdowns": 0,
    "FantasyPoints": 3.6,
    "AverageDraftPosition": 323,
    "Rank": 140
  },
  {
    "Name": "Trevor Davis",
    "Team": "GB",
    "Position": "WR",
    "ByeWeek": 7,
    "Age": 25,
    "RushingYards": 15,
    "RushingTouchdowns": 0,
    "Receptions": 9,
    "ReceivingYards": 99,
    "ReceivingTouchdowns": 0,
    "FantasyPoints": 11.4,
    "AverageDraftPosition": 325,
    "Rank": 141
  },
  {
    "Name": "Mike Thomas",
    "Team": "LAR",
    "Position": "WR",
    "ByeWeek": 12,
    "Age": 23,
    "RushingYards": 2,
    "RushingTouchdowns": 0,
    "Receptions": 6,
    "ReceivingYards": 88,
    "ReceivingTouchdowns": 0,
    "FantasyPoints": 7,
    "AverageDraftPosition": 330,
    "Rank": 142
  },
  {
    "Name": "Travis Rudolph",
    "Team": "NYG",
    "Position": "WR",
    "ByeWeek": 9,
    "Age": 22,
    "RushingYards": 1,
    "RushingTouchdowns": 0,
    "Receptions": 7,
    "ReceivingYards": 91,
    "ReceivingTouchdowns": 0,
    "FantasyPoints": 9.2,
    "AverageDraftPosition": 332,
    "Rank": 143
  },
  {
    "Name": "Justin Hunter",
    "Team": "PIT",
    "Position": "WR",
    "ByeWeek": 7,
    "Age": 27,
    "RushingYards": 0,
    "RushingTouchdowns": 0,
    "Receptions": 5,
    "ReceivingYards": 58,
    "ReceivingTouchdowns": 1,
    "FantasyPoints": 11.8,
    "AverageDraftPosition": 338,
    "Rank": 144
  },
  {
    "Name": "Justin Hardy",
    "Team": "ATL",
    "Position": "WR",
    "ByeWeek": 8,
    "Age": 26,
    "RushingYards": 0,
    "RushingTouchdowns": 0,
    "Receptions": 12,
    "ReceivingYards": 143,
    "ReceivingTouchdowns": 1,
    "FantasyPoints": 20.3,
    "AverageDraftPosition": 341,
    "Rank": 145
  },
  {
    "Name": "Russell Shepard",
    "Team": "NYG",
    "Position": "WR",
    "ByeWeek": 9,
    "Age": 27,
    "RushingYards": 3,
    "RushingTouchdowns": 0,
    "Receptions": 9,
    "ReceivingYards": 121,
    "ReceivingTouchdowns": 0,
    "FantasyPoints": 12.4,
    "AverageDraftPosition": 344,
    "Rank": 146
  },
  {
    "Name": "Jesus Wilson",
    "Team": "TB",
    "Position": "WR",
    "ByeWeek": 5,
    "Age": 23,
    "RushingYards": 12,
    "RushingTouchdowns": 0,
    "Receptions": 5,
    "ReceivingYards": 72,
    "ReceivingTouchdowns": 0,
    "FantasyPoints": 8.4,
    "AverageDraftPosition": 345,
    "Rank": 147
  },
  {
    "Name": "Deonte Thompson",
    "Team": "DAL",
    "Position": "WR",
    "ByeWeek": 8,
    "Age": 29,
    "RushingYards": 0,
    "RushingTouchdowns": 0,
    "Receptions": 10,
    "ReceivingYards": 147,
    "ReceivingTouchdowns": 0,
    "FantasyPoints": 14.7,
    "AverageDraftPosition": 349,
    "Rank": 148
  },
  {
    "Name": "Jordan Taylor",
    "Team": "DEN",
    "Position": "WR",
    "ByeWeek": 10,
    "Age": 26,
    "RushingYards": 1,
    "RushingTouchdowns": 0,
    "Receptions": 11,
    "ReceivingYards": 125,
    "ReceivingTouchdowns": 1,
    "FantasyPoints": 18.6,
    "AverageDraftPosition": 354,
    "Rank": 149
  },
  {
    "Name": "Andre Holmes",
    "Team": "BUF",
    "Position": "WR",
    "ByeWeek": 11,
    "Age": 30,
    "RushingYards": 0,
    "RushingTouchdowns": 0,
    "Receptions": 11,
    "ReceivingYards": 136,
    "ReceivingTouchdowns": 1,
    "FantasyPoints": 19.6,
    "AverageDraftPosition": 357,
    "Rank": 150
  },
  {
    "Name": "Jaydon Mickens",
    "Team": "JAX",
    "Position": "WR",
    "ByeWeek": 9,
    "Age": 24,
    "RushingYards": 0,
    "RushingTouchdowns": 0,
    "Receptions": 4,
    "ReceivingYards": 53,
    "ReceivingTouchdowns": 0,
    "FantasyPoints": 3.3,
    "AverageDraftPosition": 364,
    "Rank": 151
  },
  {
    "Name": "Kasen Williams",
    "Team": "IND",
    "Position": "WR",
    "ByeWeek": 9,
    "Age": 26,
    "RushingYards": 0,
    "RushingTouchdowns": 0,
    "Receptions": 8,
    "ReceivingYards": 89,
    "ReceivingTouchdowns": 0,
    "FantasyPoints": 8.9,
    "AverageDraftPosition": 367,
    "Rank": 152
  },
  {
    "Name": "Leonte Carroo",
    "Team": "MIA",
    "Position": "WR",
    "ByeWeek": 11,
    "Age": 24,
    "RushingYards": 0,
    "RushingTouchdowns": 0,
    "Receptions": 6,
    "ReceivingYards": 58,
    "ReceivingTouchdowns": 0,
    "FantasyPoints": 5.8,
    "AverageDraftPosition": 368,
    "Rank": 153
  },
  {
    "Name": "Josh Bellamy",
    "Team": "CHI",
    "Position": "WR",
    "ByeWeek": 5,
    "Age": 29,
    "RushingYards": 2,
    "RushingTouchdowns": 0,
    "Receptions": 9,
    "ReceivingYards": 130,
    "ReceivingTouchdowns": 0,
    "FantasyPoints": 13.2,
    "AverageDraftPosition": 372,
    "Rank": 154
  },
  {
    "Name": "Braxton Berrios",
    "Team": "NE",
    "Position": "WR",
    "ByeWeek": 11,
    "Age": 22,
    "RushingYards": 0,
    "RushingTouchdowns": 0,
    "Receptions": 5,
    "ReceivingYards": 70,
    "ReceivingTouchdowns": 0,
    "FantasyPoints": 7,
    "AverageDraftPosition": 377,
    "Rank": 155
  },
  {
    "Name": "Bruce Ellington",
    "Team": "HOU",
    "Position": "WR",
    "ByeWeek": 10,
    "Age": 26,
    "RushingYards": 11,
    "RushingTouchdowns": 0,
    "Receptions": 18,
    "ReceivingYards": 273,
    "ReceivingTouchdowns": 1,
    "FantasyPoints": 34.4,
    "AverageDraftPosition": 378,
    "Rank": 156
  },
  {
    "Name": "Richie James",
    "Team": "SF",
    "Position": "WR",
    "ByeWeek": 11,
    "Age": 22,
    "RushingYards": 0,
    "RushingTouchdowns": 0,
    "Receptions": 5,
    "ReceivingYards": 69,
    "ReceivingTouchdowns": 0,
    "FantasyPoints": 6.9,
    "AverageDraftPosition": 379,
    "Rank": 157
  },
  {
    "Name": "Maxwell McCaffrey",
    "Team": "SF",
    "Position": "WR",
    "ByeWeek": 11,
    "Age": 24,
    "RushingYards": 0,
    "RushingTouchdowns": 0,
    "Receptions": 6,
    "ReceivingYards": 63,
    "ReceivingTouchdowns": 0,
    "FantasyPoints": 6.3,
    "AverageDraftPosition": 384,
    "Rank": 158
  },
  {
    "Name": "Ardarius Stewart",
    "Team": "NYJ",
    "Position": "WR",
    "ByeWeek": 11,
    "Age": 24,
    "RushingYards": 20,
    "RushingTouchdowns": 0,
    "Receptions": 4,
    "ReceivingYards": 51,
    "ReceivingTouchdowns": 0,
    "FantasyPoints": 7.1,
    "AverageDraftPosition": 387,
    "Rank": 159
  },
  {
    "Name": "Justin Watson",
    "Team": "TB",
    "Position": "WR",
    "ByeWeek": 5,
    "Age": 23,
    "RushingYards": 0,
    "RushingTouchdowns": 0,
    "Receptions": 3,
    "ReceivingYards": 39,
    "ReceivingTouchdowns": 0,
    "FantasyPoints": 3.9,
    "AverageDraftPosition": 388,
    "Rank": 160
  },
  {
    "Name": "Trey Quinn",
    "Team": "WAS",
    "Position": "WR",
    "ByeWeek": 4,
    "Age": 22,
    "RushingYards": 0,
    "RushingTouchdowns": 0,
    "Receptions": 5,
    "ReceivingYards": 63,
    "ReceivingTouchdowns": 0,
    "FantasyPoints": 6.3,
    "AverageDraftPosition": 389,
    "Rank": 161
  },
  {
    "Name": "Tajae Sharpe",
    "Team": "TEN",
    "Position": "WR",
    "ByeWeek": 8,
    "Age": 23,
    "RushingYards": 2,
    "RushingTouchdowns": 0,
    "Receptions": 10,
    "ReceivingYards": 200,
    "ReceivingTouchdowns": 1,
    "FantasyPoints": 26.2,
    "AverageDraftPosition": 391,
    "Rank": 162
  },
  {
    "Name": "Cody Core",
    "Team": "CIN",
    "Position": "WR",
    "ByeWeek": 9,
    "Age": 24,
    "RushingYards": 0,
    "RushingTouchdowns": 0,
    "Receptions": 5,
    "ReceivingYards": 63,
    "ReceivingTouchdowns": 0,
    "FantasyPoints": 6.3,
    "AverageDraftPosition": 392,
    "Rank": 163
  },
  {
    "Name": "Rod Streater",
    "Team": "BUF",
    "Position": "WR",
    "ByeWeek": 11,
    "Age": 30,
    "RushingYards": 0,
    "RushingTouchdowns": 0,
    "Receptions": 6,
    "ReceivingYards": 65,
    "ReceivingTouchdowns": 0,
    "FantasyPoints": 6.5,
    "AverageDraftPosition": 395,
    "Rank": 164
  },
  {
    "Name": "Charone Peake",
    "Team": "NYJ",
    "Position": "WR",
    "ByeWeek": 11,
    "Age": 25,
    "RushingYards": 0,
    "RushingTouchdowns": 0,
    "Receptions": 7,
    "ReceivingYards": 77,
    "ReceivingTouchdowns": 0,
    "FantasyPoints": 7.7,
    "AverageDraftPosition": 397,
    "Rank": 165
  },
  {
    "Name": "Damion Ratley",
    "Team": "CLE",
    "Position": "WR",
    "ByeWeek": 11,
    "Age": 23,
    "RushingYards": 0,
    "RushingTouchdowns": 0,
    "Receptions": 5,
    "ReceivingYards": 62,
    "ReceivingTouchdowns": 0,
    "FantasyPoints": 6.2,
    "AverageDraftPosition": 398,
    "Rank": 166
  },
  {
    "Name": "Marcus Johnson",
    "Team": "SEA",
    "Position": "WR",
    "ByeWeek": 7,
    "Age": 24,
    "RushingYards": 0,
    "RushingTouchdowns": 0,
    "Receptions": 4,
    "ReceivingYards": 44,
    "ReceivingTouchdowns": 0,
    "FantasyPoints": 4.4,
    "AverageDraftPosition": 400,
    "Rank": 167
  },
  {
    "Name": "Marcell Ateman",
    "Team": "OAK",
    "Position": "WR",
    "ByeWeek": 7,
    "Age": 23,
    "RushingYards": 0,
    "RushingTouchdowns": 0,
    "Receptions": 4,
    "ReceivingYards": 56,
    "ReceivingTouchdowns": 0,
    "FantasyPoints": 5.6,
    "AverageDraftPosition": 411,
    "Rank": 168
  },
  {
    "Name": "Javon Wims",
    "Team": "CHI",
    "Position": "WR",
    "ByeWeek": 5,
    "Age": 23,
    "RushingYards": 0,
    "RushingTouchdowns": 0,
    "Receptions": 4,
    "ReceivingYards": 53,
    "ReceivingTouchdowns": 0,
    "FantasyPoints": 5.3,
    "AverageDraftPosition": 413,
    "Rank": 169
  },
  {
    "Name": "Austin Carr",
    "Team": "NO",
    "Position": "WR",
    "ByeWeek": 6,
    "Age": 24,
    "RushingYards": 0,
    "RushingTouchdowns": 0,
    "Receptions": 3,
    "ReceivingYards": 42,
    "ReceivingTouchdowns": 0,
    "FantasyPoints": 4.2,
    "AverageDraftPosition": 414,
    "Rank": 170
  },
  {
    "Name": "Dylan Cantrell",
    "Team": "LAC",
    "Position": "WR",
    "ByeWeek": 8,
    "Age": 24,
    "RushingYards": 3,
    "RushingTouchdowns": 0,
    "Receptions": 2,
    "ReceivingYards": 98,
    "ReceivingTouchdowns": 0,
    "FantasyPoints": 10.1,
    "AverageDraftPosition": 419,
    "Rank": 171
  },
  {
    "Name": "Aaron Burbridge",
    "Team": "SF",
    "Position": "WR",
    "ByeWeek": 11,
    "Age": 24,
    "RushingYards": 0,
    "RushingTouchdowns": 0,
    "Receptions": 3,
    "ReceivingYards": 46,
    "ReceivingTouchdowns": 0,
    "FantasyPoints": 4.6,
    "AverageDraftPosition": 420,
    "Rank": 172
  },
  {
    "Name": "Shane Wynn",
    "Team": "JAX",
    "Position": "WR",
    "ByeWeek": 9,
    "Age": 25,
    "RushingYards": 0,
    "RushingTouchdowns": 0,
    "Receptions": 3,
    "ReceivingYards": 50,
    "ReceivingTouchdowns": 0,
    "FantasyPoints": 5,
    "AverageDraftPosition": 421,
    "Rank": 173
  },
  {
    "Name": "Shelton Gibson",
    "Team": "PHI",
    "Position": "WR",
    "ByeWeek": 9,
    "Age": 24,
    "RushingYards": 0,
    "RushingTouchdowns": 0,
    "Receptions": 3,
    "ReceivingYards": 33,
    "ReceivingTouchdowns": 0,
    "FantasyPoints": 3.3,
    "AverageDraftPosition": 422,
    "Rank": 174
  },
  {
    "Name": "Reggie Davis",
    "Team": "ATL",
    "Position": "WR",
    "ByeWeek": 8,
    "Age": 22,
    "RushingYards": 4,
    "RushingTouchdowns": 0,
    "Receptions": 3,
    "ReceivingYards": 78,
    "ReceivingTouchdowns": 0,
    "FantasyPoints": 8.2,
    "AverageDraftPosition": 423,
    "Rank": 175
  },
  {
    "Name": "Russell Gage",
    "Team": "ATL",
    "Position": "WR",
    "ByeWeek": 8,
    "Age": 22,
    "RushingYards": 0,
    "RushingTouchdowns": 0,
    "Receptions": 2,
    "ReceivingYards": 38,
    "ReceivingTouchdowns": 0,
    "FantasyPoints": 3.8,
    "AverageDraftPosition": 424,
    "Rank": 176
  },
  {
    "Name": "Auden Tate",
    "Team": "CIN",
    "Position": "WR",
    "ByeWeek": 9,
    "Age": 21,
    "RushingYards": 0,
    "RushingTouchdowns": 0,
    "Receptions": 4,
    "ReceivingYards": 50,
    "ReceivingTouchdowns": 0,
    "FantasyPoints": 5,
    "AverageDraftPosition": 425,
    "Rank": 177
  },
  {
    "Name": "Darrius Heyward-Bey",
    "Team": "PIT",
    "Position": "WR",
    "ByeWeek": 7,
    "Age": 31,
    "RushingYards": 20,
    "RushingTouchdowns": 0,
    "Receptions": 3,
    "ReceivingYards": 47,
    "ReceivingTouchdowns": 0,
    "FantasyPoints": 6.7,
    "AverageDraftPosition": 428,
    "Rank": 178
  },
  {
    "Name": "Tanner Gentry",
    "Team": "CHI",
    "Position": "WR",
    "ByeWeek": 5,
    "Age": 23,
    "RushingYards": 0,
    "RushingTouchdowns": 0,
    "Receptions": 4,
    "ReceivingYards": 38,
    "ReceivingTouchdowns": 0,
    "FantasyPoints": 3.8,
    "AverageDraftPosition": 429,
    "Rank": 179
  },
  {
    "Name": "Daurice Fountain",
    "Team": "IND",
    "Position": "WR",
    "ByeWeek": 9,
    "Age": 22,
    "RushingYards": 3,
    "RushingTouchdowns": 0,
    "Receptions": 5,
    "ReceivingYards": 103,
    "ReceivingTouchdowns": 1,
    "FantasyPoints": 16.6,
    "AverageDraftPosition": 431,
    "Rank": 180
  },
  {
    "Name": "Jarius Wright",
    "Team": "CAR",
    "Position": "WR",
    "ByeWeek": 4,
    "Age": 28,
    "RushingYards": 2,
    "RushingTouchdowns": 0,
    "Receptions": 27,
    "ReceivingYards": 350,
    "ReceivingTouchdowns": 2,
    "FantasyPoints": 47.2,
    "AverageDraftPosition": 437,
    "Rank": 181
  },
  {
    "Name": "De'Anthony Thomas",
    "Team": "KC",
    "Position": "WR",
    "ByeWeek": 12,
    "Age": 25,
    "RushingYards": 11,
    "RushingTouchdowns": 0,
    "Receptions": 5,
    "ReceivingYards": 48,
    "ReceivingTouchdowns": 1,
    "FantasyPoints": 11.9,
    "AverageDraftPosition": 438,
    "Rank": 182
  },
  {
    "Name": "Noah Brown",
    "Team": "DAL",
    "Position": "WR",
    "ByeWeek": 8,
    "Age": 22,
    "RushingYards": 0,
    "RushingTouchdowns": 0,
    "Receptions": 4,
    "ReceivingYards": 38,
    "ReceivingTouchdowns": 0,
    "FantasyPoints": 3.8,
    "AverageDraftPosition": 440,
    "Rank": 183
  },
  {
    "Name": "Ray-Ray McCloud",
    "Team": "BUF",
    "Position": "WR",
    "ByeWeek": 11,
    "Age": 21,
    "RushingYards": 0,
    "RushingTouchdowns": 0,
    "Receptions": 4,
    "ReceivingYards": 45,
    "ReceivingTouchdowns": 0,
    "FantasyPoints": 4.5,
    "AverageDraftPosition": 441,
    "Rank": 184
  },
  {
    "Name": "Austin Proehl",
    "Team": "BUF",
    "Position": "WR",
    "ByeWeek": 11,
    "Age": 22,
    "RushingYards": 0,
    "RushingTouchdowns": 0,
    "Receptions": 4,
    "ReceivingYards": 45,
    "ReceivingTouchdowns": 0,
    "FantasyPoints": 4.5,
    "AverageDraftPosition": 442,
    "Rank": 185
  },
  {
    "Name": "Andy Jones",
    "Team": "DET",
    "Position": "WR",
    "ByeWeek": 6,
    "Age": 24,
    "RushingYards": 0,
    "RushingTouchdowns": 0,
    "Receptions": 3,
    "ReceivingYards": 35,
    "ReceivingTouchdowns": 0,
    "FantasyPoints": 3.5,
    "AverageDraftPosition": 445,
    "Rank": 186
  },
  {
    "Name": "Daniel Brown",
    "Team": "CHI",
    "Position": "WR",
    "ByeWeek": 5,
    "Age": 26,
    "RushingYards": 0,
    "RushingTouchdowns": 0,
    "Receptions": 4,
    "ReceivingYards": 32,
    "ReceivingTouchdowns": 0,
    "FantasyPoints": 3.2,
    "AverageDraftPosition": 446,
    "Rank": 187
  },
  {
    "Name": "Chris Thompson",
    "Team": "HOU",
    "Position": "WR",
    "ByeWeek": 10,
    "Age": 24,
    "RushingYards": 0,
    "RushingTouchdowns": 0,
    "Receptions": 3,
    "ReceivingYards": 42,
    "ReceivingTouchdowns": 0,
    "FantasyPoints": 4.2,
    "AverageDraftPosition": 447,
    "Rank": 188
  },
  {
    "Name": "Deon Cain",
    "Team": "IND",
    "Position": "WR",
    "ByeWeek": 9,
    "Age": 21,
    "RushingYards": 3,
    "RushingTouchdowns": 0,
    "Receptions": 25,
    "ReceivingYards": 357,
    "ReceivingTouchdowns": 2,
    "FantasyPoints": 48,
    "AverageDraftPosition": 448,
    "Rank": 189
  },
  {
    "Name": "Phillip Dorsett",
    "Team": "NE",
    "Position": "WR",
    "ByeWeek": 11,
    "Age": 25,
    "RushingYards": 1,
    "RushingTouchdowns": 0,
    "Receptions": 12,
    "ReceivingYards": 163,
    "ReceivingTouchdowns": 0,
    "FantasyPoints": 16.4,
    "AverageDraftPosition": 450,
    "Rank": 190
  },
  {
    "Name": "Kaelin Clay",
    "Team": "BUF",
    "Position": "WR",
    "ByeWeek": 11,
    "Age": 26,
    "RushingYards": 3,
    "RushingTouchdowns": 0,
    "Receptions": 4,
    "ReceivingYards": 71,
    "ReceivingTouchdowns": 0,
    "FantasyPoints": 5.4,
    "AverageDraftPosition": 451,
    "Rank": 191
  },
  {
    "Name": "Maurice Harris",
    "Team": "WAS",
    "Position": "WR",
    "ByeWeek": 4,
    "Age": 25,
    "RushingYards": 0,
    "RushingTouchdowns": 0,
    "Receptions": 4,
    "ReceivingYards": 62,
    "ReceivingTouchdowns": 0,
    "FantasyPoints": 6.2,
    "AverageDraftPosition": 460,
    "Rank": 192
  },
  {
    "Name": "Alex Erickson",
    "Team": "CIN",
    "Position": "WR",
    "ByeWeek": 9,
    "Age": 25,
    "RushingYards": 7,
    "RushingTouchdowns": 0,
    "Receptions": 4,
    "ReceivingYards": 63,
    "ReceivingTouchdowns": 0,
    "FantasyPoints": 7,
    "AverageDraftPosition": 466,
    "Rank": 193
  },
  {
    "Name": "Brandon Reilly",
    "Team": "BUF",
    "Position": "WR",
    "ByeWeek": 11,
    "Age": 24,
    "RushingYards": 2,
    "RushingTouchdowns": 0,
    "Receptions": 4,
    "ReceivingYards": 125,
    "ReceivingTouchdowns": 1,
    "FantasyPoints": 18.7,
    "AverageDraftPosition": 467,
    "Rank": 194
  },
  {
    "Name": "Chad Hansen",
    "Team": "NYJ",
    "Position": "WR",
    "ByeWeek": 11,
    "Age": 23,
    "RushingYards": 1,
    "RushingTouchdowns": 0,
    "Receptions": 5,
    "ReceivingYards": 80,
    "ReceivingTouchdowns": 0,
    "FantasyPoints": 8.1,
    "AverageDraftPosition": 470,
    "Rank": 195
  },
  {
    "Name": "Bryce Treggs",
    "Team": "PHI",
    "Position": "WR",
    "ByeWeek": 9,
    "Age": 24,
    "RushingYards": 7,
    "RushingTouchdowns": 0,
    "Receptions": 6,
    "ReceivingYards": 86,
    "ReceivingTouchdowns": 0,
    "FantasyPoints": 9.3,
    "AverageDraftPosition": 471,
    "Rank": 196
  },
  {
    "Name": "Brandon Coleman",
    "Team": "NO",
    "Position": "WR",
    "ByeWeek": 6,
    "Age": 26,
    "RushingYards": 0,
    "RushingTouchdowns": 0,
    "Receptions": 10,
    "ReceivingYards": 164,
    "ReceivingTouchdowns": 1,
    "FantasyPoints": 22.4,
    "AverageDraftPosition": 472,
    "Rank": 197
  },
  {
    "Name": "Damiere Byrd",
    "Team": "CAR",
    "Position": "WR",
    "ByeWeek": 4,
    "Age": 25,
    "RushingYards": 14,
    "RushingTouchdowns": 0,
    "Receptions": 5,
    "ReceivingYards": 75,
    "ReceivingTouchdowns": 0,
    "FantasyPoints": 8.9,
    "AverageDraftPosition": 477,
    "Rank": 198
  },
  {
    "Name": "Seantavious Jones",
    "Team": "IND",
    "Position": "WR",
    "ByeWeek": 9,
    "Age": 25,
    "RushingYards": 0,
    "RushingTouchdowns": 0,
    "Receptions": 4,
    "ReceivingYards": 38,
    "ReceivingTouchdowns": 0,
    "FantasyPoints": 3.8,
    "AverageDraftPosition": 479,
    "Rank": 199
  },
  {
    "Name": "Jehu Chesson",
    "Team": "KC",
    "Position": "WR",
    "ByeWeek": 12,
    "Age": 24,
    "RushingYards": 0,
    "RushingTouchdowns": 0,
    "Receptions": 2,
    "ReceivingYards": 24,
    "ReceivingTouchdowns": 0,
    "FantasyPoints": 2.4,
    "AverageDraftPosition": 485,
    "Rank": 200
  },
  {
    "Name": "Markus Wheaton",
    "Team": "PHI",
    "Position": "WR",
    "ByeWeek": 9,
    "Age": 27,
    "RushingYards": 0,
    "RushingTouchdowns": 0,
    "Receptions": 3,
    "ReceivingYards": 67,
    "ReceivingTouchdowns": 0,
    "FantasyPoints": 6.7,
    "AverageDraftPosition": 488,
    "Rank": 201
  },
  {
    "Name": "Josh Malone",
    "Team": "CIN",
    "Position": "WR",
    "ByeWeek": 9,
    "Age": 22,
    "RushingYards": 12,
    "RushingTouchdowns": 0,
    "Receptions": 3,
    "ReceivingYards": 72,
    "ReceivingTouchdowns": 0,
    "FantasyPoints": 8.4,
    "AverageDraftPosition": 489,
    "Rank": 202
  },
  {
    "Name": "Michael Campanaro",
    "Team": "TEN",
    "Position": "WR",
    "ByeWeek": 8,
    "Age": 27,
    "RushingYards": 7,
    "RushingTouchdowns": 0,
    "Receptions": 5,
    "ReceivingYards": 98,
    "ReceivingTouchdowns": 0,
    "FantasyPoints": 10.5,
    "AverageDraftPosition": 497,
    "Rank": 203
  },
  {
    "Name": "Marvin Hall",
    "Team": "ATL",
    "Position": "WR",
    "ByeWeek": 8,
    "Age": 25,
    "RushingYards": 2,
    "RushingTouchdowns": 0,
    "Receptions": 2,
    "ReceivingYards": 54,
    "ReceivingTouchdowns": 0,
    "FantasyPoints": 5.6,
    "AverageDraftPosition": 498,
    "Rank": 204
  },
  {
    "Name": "Jeff Janis",
    "Team": "CLE",
    "Position": "WR",
    "ByeWeek": 11,
    "Age": 27,
    "RushingYards": 0,
    "RushingTouchdowns": 0,
    "Receptions": 2,
    "ReceivingYards": 24,
    "ReceivingTouchdowns": 0,
    "FantasyPoints": 2.4,
    "AverageDraftPosition": 502,
    "Rank": 205
  },
  {
    "Name": "Dwayne Harris",
    "Team": "OAK",
    "Position": "WR",
    "ByeWeek": 7,
    "Age": 30,
    "RushingYards": 0,
    "RushingTouchdowns": 0,
    "Receptions": 1,
    "ReceivingYards": 25,
    "ReceivingTouchdowns": 0,
    "FantasyPoints": 2.5,
    "AverageDraftPosition": 505,
    "Rank": 206
  },
  {
    "Name": "Aldrick Robinson",
    "Team": "SF",
    "Position": "WR",
    "ByeWeek": 11,
    "Age": 29,
    "RushingYards": 0,
    "RushingTouchdowns": 0,
    "Receptions": 12,
    "ReceivingYards": 141,
    "ReceivingTouchdowns": 1,
    "FantasyPoints": 20.1,
    "AverageDraftPosition": 512,
    "Rank": 207
  },
  {
    "Name": "Breshad Perriman",
    "Team": "BAL",
    "Position": "WR",
    "ByeWeek": 10,
    "Age": 22,
    "RushingYards": 0,
    "RushingTouchdowns": 0,
    "Receptions": 8,
    "ReceivingYards": 127,
    "ReceivingTouchdowns": 1,
    "FantasyPoints": 18.7,
    "AverageDraftPosition": 529,
    "Rank": 208
  },
  {
    "Name": "Tavarres King",
    "Team": "MIN",
    "Position": "WR",
    "ByeWeek": 10,
    "Age": 28,
    "RushingYards": 1,
    "RushingTouchdowns": 0,
    "Receptions": 5,
    "ReceivingYards": 70,
    "ReceivingTouchdowns": 1,
    "FantasyPoints": 13.1,
    "AverageDraftPosition": 538,
    "Rank": 209
  },
  {
    "Name": "Tommylee Lewis",
    "Team": "NO",
    "Position": "WR",
    "ByeWeek": 6,
    "Age": 25,
    "RushingYards": 16,
    "RushingTouchdowns": 0,
    "Receptions": 3,
    "ReceivingYards": 26,
    "ReceivingTouchdowns": 0,
    "FantasyPoints": 2.2,
    "AverageDraftPosition": 550,
    "Rank": 210
  },
  {
    "Name": "Sammie Coates",
    "Team": "HOU",
    "Position": "WR",
    "ByeWeek": 10,
    "Age": 25,
    "RushingYards": 0,
    "RushingTouchdowns": 0,
    "Receptions": 2,
    "ReceivingYards": 61,
    "ReceivingTouchdowns": 0,
    "FantasyPoints": 6.1,
    "AverageDraftPosition": 562,
    "Rank": 211
  },
  {
    "Name": "Freddie Martino",
    "Team": "TB",
    "Position": "WR",
    "ByeWeek": 5,
    "Age": 26,
    "RushingYards": 0,
    "RushingTouchdowns": 0,
    "Receptions": 2,
    "ReceivingYards": 60,
    "ReceivingTouchdowns": 0,
    "FantasyPoints": 6,
    "AverageDraftPosition": 563,
    "Rank": 212
  },
  {
    "Name": "Pharoh Cooper",
    "Team": "LAR",
    "Position": "WR",
    "ByeWeek": 12,
    "Age": 23,
    "RushingYards": 2,
    "RushingTouchdowns": 0,
    "Receptions": 9,
    "ReceivingYards": 110,
    "ReceivingTouchdowns": 0,
    "FantasyPoints": 9.2,
    "AverageDraftPosition": 564,
    "Rank": 213
  },
  {
    "Name": "Khalif Raymond",
    "Team": "NYG",
    "Position": "WR",
    "ByeWeek": 9,
    "Age": 23,
    "RushingYards": 1,
    "RushingTouchdowns": 0,
    "Receptions": 2,
    "ReceivingYards": 29,
    "ReceivingTouchdowns": 0,
    "FantasyPoints": 1,
    "AverageDraftPosition": 575,
    "Rank": 214
  },
  {
    "Name": "Brian Quick",
    "Team": "WAS",
    "Position": "WR",
    "ByeWeek": 4,
    "Age": 29,
    "RushingYards": 0,
    "RushingTouchdowns": 0,
    "Receptions": 12,
    "ReceivingYards": 146,
    "ReceivingTouchdowns": 0,
    "FantasyPoints": 14.6,
    "AverageDraftPosition": 580,
    "Rank": 215
  },
  {
    "Name": "Quan Bray",
    "Team": "BUF",
    "Position": "WR",
    "ByeWeek": 11,
    "Age": 25,
    "RushingYards": 0,
    "RushingTouchdowns": 0,
    "Receptions": 2,
    "ReceivingYards": 24,
    "ReceivingTouchdowns": 0,
    "FantasyPoints": 2.4,
    "AverageDraftPosition": 581,
    "Rank": 216
  },
  {
    "Name": "Geremy Davis",
    "Team": "LAC",
    "Position": "WR",
    "ByeWeek": 8,
    "Age": 26,
    "RushingYards": 0,
    "RushingTouchdowns": 0,
    "Receptions": 1,
    "ReceivingYards": 22,
    "ReceivingTouchdowns": 0,
    "FantasyPoints": 2.2,
    "AverageDraftPosition": 582,
    "Rank": 217
  },
  {
    "Name": "Nick Williams",
    "Team": "TEN",
    "Position": "WR",
    "ByeWeek": 8,
    "Age": 27,
    "RushingYards": 0,
    "RushingTouchdowns": 0,
    "Receptions": 2,
    "ReceivingYards": 24,
    "ReceivingTouchdowns": 0,
    "FantasyPoints": 2.4,
    "AverageDraftPosition": 583,
    "Rank": 218
  },
  {
    "Name": "Deandrew White",
    "Team": "HOU",
    "Position": "WR",
    "ByeWeek": 10,
    "Age": 26,
    "RushingYards": 0,
    "RushingTouchdowns": 0,
    "Receptions": 2,
    "ReceivingYards": 28,
    "ReceivingTouchdowns": 0,
    "FantasyPoints": 2.8,
    "AverageDraftPosition": 584,
    "Rank": 219
  },
  {
    "Name": "Tre McBride",
    "Team": "NYJ",
    "Position": "WR",
    "ByeWeek": 11,
    "Age": 25,
    "RushingYards": 0,
    "RushingTouchdowns": 0,
    "Receptions": 1,
    "ReceivingYards": 15,
    "ReceivingTouchdowns": 0,
    "FantasyPoints": 1.5,
    "AverageDraftPosition": 608,
    "Rank": 220
  },
  {
    "Name": "Stacy Coley",
    "Team": "MIN",
    "Position": "WR",
    "ByeWeek": 10,
    "Age": 24,
    "RushingYards": 0,
    "RushingTouchdowns": 0,
    "Receptions": 1,
    "ReceivingYards": 57,
    "ReceivingTouchdowns": 0,
    "FantasyPoints": 5.7,
    "AverageDraftPosition": 609,
    "Rank": 221
  },
  {
    "Name": "Eric Decker",
    "Team": "NE",
    "Position": "WR",
    "ByeWeek": 11,
    "Age": 31,
    "RushingYards": 0,
    "RushingTouchdowns": 0,
    "Receptions": 1,
    "ReceivingYards": 16,
    "ReceivingTouchdowns": 0,
    "FantasyPoints": 1.6,
    "AverageDraftPosition": 684,
    "Rank": 222
  },
  {
    "Name": "Eli Rogers",
    "Team": "PIT",
    "Position": "WR",
    "ByeWeek": 7,
    "Age": 25,
    "RushingYards": 0,
    "RushingTouchdowns": 0,
    "Receptions": 13,
    "ReceivingYards": 137,
    "ReceivingTouchdowns": 1,
    "FantasyPoints": 17.7,
    "AverageDraftPosition": 686,
    "Rank": 223
  },
  {
    "Name": "Kamar Aiken",
    "Team": "PHI",
    "Position": "WR",
    "ByeWeek": 9,
    "Age": 29,
    "RushingYards": 0,
    "RushingTouchdowns": 0,
    "Receptions": 0,
    "ReceivingYards": 0,
    "ReceivingTouchdowns": 0,
    "FantasyPoints": 0,
    "AverageDraftPosition": 688,
    "Rank": 224
  },
  {
    "Name": "Michael Floyd",
    "Team": "NO",
    "Position": "WR",
    "ByeWeek": 6,
    "Age": 28,
    "RushingYards": 0,
    "RushingTouchdowns": 0,
    "Receptions": 3,
    "ReceivingYards": 31,
    "ReceivingTouchdowns": 0,
    "FantasyPoints": 3.1,
    "AverageDraftPosition": 690,
    "Rank": 225
  },
  {
    "Name": "Deangelo Yancey",
    "Team": "GB",
    "Position": "WR",
    "ByeWeek": 7,
    "Age": 23,
    "RushingYards": 3,
    "RushingTouchdowns": 0,
    "Receptions": 4,
    "ReceivingYards": 149,
    "ReceivingTouchdowns": 1,
    "FantasyPoints": 21.2,
    "AverageDraftPosition": 693,
    "Rank": 226
  },
  {
    "Name": "Rashad Greene",
    "Team": "JAX",
    "Position": "WR",
    "ByeWeek": 9,
    "Age": 25,
    "RushingYards": 0,
    "RushingTouchdowns": 0,
    "Receptions": 1,
    "ReceivingYards": 10,
    "ReceivingTouchdowns": 0,
    "FantasyPoints": 1,
    "AverageDraftPosition": 695,
    "Rank": 227
  },
  {
    "Name": "DeAndre Smelter",
    "Team": "JAX",
    "Position": "WR",
    "ByeWeek": 9,
    "Age": 26,
    "RushingYards": 0,
    "RushingTouchdowns": 0,
    "Receptions": 1,
    "ReceivingYards": 16,
    "ReceivingTouchdowns": 0,
    "FantasyPoints": 1.6,
    "AverageDraftPosition": 699,
    "Rank": 228
  },
  {
    "Name": "Robert Davis",
    "Team": "WAS",
    "Position": "WR",
    "ByeWeek": 4,
    "Age": 23,
    "RushingYards": 0,
    "RushingTouchdowns": 0,
    "Receptions": 0,
    "ReceivingYards": 0,
    "ReceivingTouchdowns": 0,
    "FantasyPoints": 0,
    "AverageDraftPosition": 700,
    "Rank": 229
  },
  {
    "Name": "Darius Jennings",
    "Team": "TEN",
    "Position": "WR",
    "ByeWeek": 8,
    "Age": 26,
    "RushingYards": 0,
    "RushingTouchdowns": 0,
    "Receptions": 6,
    "ReceivingYards": 71,
    "ReceivingTouchdowns": 1,
    "FantasyPoints": 13.1,
    "AverageDraftPosition": 701,
    "Rank": 230
  },
  {
    "Name": "Jake Lampman",
    "Team": "TB",
    "Position": "WR",
    "ByeWeek": 5,
    "Age": 25,
    "RushingYards": 0,
    "RushingTouchdowns": 0,
    "Receptions": 6,
    "ReceivingYards": 72,
    "ReceivingTouchdowns": 0,
    "FantasyPoints": 7.2,
    "AverageDraftPosition": 702,
    "Rank": 231
  },
  {
    "Name": "Daniel Braverman",
    "Team": "KC",
    "Position": "WR",
    "ByeWeek": 12,
    "Age": 24,
    "RushingYards": 0,
    "RushingTouchdowns": 0,
    "Receptions": 5,
    "ReceivingYards": 58,
    "ReceivingTouchdowns": 1,
    "FantasyPoints": 11.8,
    "AverageDraftPosition": 706,
    "Rank": 232
  },
  {
    "Name": "Vince Mayle",
    "Team": "BAL",
    "Position": "WR",
    "ByeWeek": 10,
    "Age": 27,
    "RushingYards": 0,
    "RushingTouchdowns": 0,
    "Receptions": 0,
    "ReceivingYards": 0,
    "ReceivingTouchdowns": 0,
    "FantasyPoints": 0,
    "AverageDraftPosition": 707,
    "Rank": 233
  },
  {
    "Name": "Jace Billingsley",
    "Team": "DET",
    "Position": "WR",
    "ByeWeek": 6,
    "Age": 25,
    "RushingYards": 0,
    "RushingTouchdowns": 0,
    "Receptions": 2,
    "ReceivingYards": 25,
    "ReceivingTouchdowns": 0,
    "FantasyPoints": 2.5,
    "AverageDraftPosition": 708,
    "Rank": 234
  },
  {
    "Name": "Demarcus Ayers",
    "Team": "CHI",
    "Position": "WR",
    "ByeWeek": 5,
    "Age": 24,
    "RushingYards": 0,
    "RushingTouchdowns": 0,
    "Receptions": 5,
    "ReceivingYards": 58,
    "ReceivingTouchdowns": 0,
    "FantasyPoints": 5.8,
    "AverageDraftPosition": 709,
    "Rank": 235
  },
  {
    "Name": "Kenny Bell",
    "Team": "DEN",
    "Position": "WR",
    "ByeWeek": 10,
    "Age": 26,
    "RushingYards": 0,
    "RushingTouchdowns": 0,
    "Receptions": 1,
    "ReceivingYards": 14,
    "ReceivingTouchdowns": 0,
    "FantasyPoints": 1.4,
    "AverageDraftPosition": 714,
    "Rank": 236
  },
  {
    "Name": "Bradley Marquez",
    "Team": "DET",
    "Position": "WR",
    "ByeWeek": 6,
    "Age": 25,
    "RushingYards": 0,
    "RushingTouchdowns": 0,
    "Receptions": 5,
    "ReceivingYards": 59,
    "ReceivingTouchdowns": 0,
    "FantasyPoints": 5.9,
    "AverageDraftPosition": 717,
    "Rank": 237
  },
  {
    "Name": "Cayleb Jones",
    "Team": "MIN",
    "Position": "WR",
    "ByeWeek": 10,
    "Age": 25,
    "RushingYards": 1,
    "RushingTouchdowns": 0,
    "Receptions": 0,
    "ReceivingYards": 122,
    "ReceivingTouchdowns": 1,
    "FantasyPoints": 18.3,
    "AverageDraftPosition": 719,
    "Rank": 238
  },
  {
    "Name": "Matthew Slater",
    "Team": "NE",
    "Position": "WR",
    "ByeWeek": 11,
    "Age": 32,
    "RushingYards": 0,
    "RushingTouchdowns": 0,
    "Receptions": 1,
    "ReceivingYards": 16,
    "ReceivingTouchdowns": 0,
    "FantasyPoints": 1.6,
    "AverageDraftPosition": 720,
    "Rank": 239
  },
  {
    "Name": "Neal Sterling",
    "Team": "NYJ",
    "Position": "WR",
    "ByeWeek": 11,
    "Age": 26,
    "RushingYards": 0,
    "RushingTouchdowns": 0,
    "Receptions": 6,
    "ReceivingYards": 79,
    "ReceivingTouchdowns": 0,
    "FantasyPoints": 7.9,
    "AverageDraftPosition": 733,
    "Rank": 240
  },
  {
    "Name": "Darren Waller",
    "Team": "BAL",
    "Position": "WR",
    "ByeWeek": 10,
    "Age": 26,
    "RushingYards": 0,
    "RushingTouchdowns": 0,
    "Receptions": 0,
    "ReceivingYards": 0,
    "ReceivingTouchdowns": 0,
    "FantasyPoints": 0,
    "AverageDraftPosition": 747,
    "Rank": 241
  },
  {
    "Name": "Rashad Ross",
    "Team": "ARI",
    "Position": "WR",
    "ByeWeek": 9,
    "Age": 28,
    "RushingYards": 0,
    "RushingTouchdowns": 0,
    "Receptions": 2,
    "ReceivingYards": 25,
    "ReceivingTouchdowns": 0,
    "FantasyPoints": 2.5,
    "AverageDraftPosition": 769,
    "Rank": 242
  },
  {
    "Name": "James Wright",
    "Team": "IND",
    "Position": "WR",
    "ByeWeek": 9,
    "Age": 26,
    "RushingYards": 0,
    "RushingTouchdowns": 0,
    "Receptions": 6,
    "ReceivingYards": 86,
    "ReceivingTouchdowns": 0,
    "FantasyPoints": 8.6,
    "AverageDraftPosition": 770,
    "Rank": 243
  },
  {
    "Name": "Dres Anderson",
    "Team": "IND",
    "Position": "WR",
    "ByeWeek": 9,
    "Age": 26,
    "RushingYards": 0,
    "RushingTouchdowns": 0,
    "Receptions": 0,
    "ReceivingYards": 75,
    "ReceivingTouchdowns": 0,
    "FantasyPoints": 7.5,
    "AverageDraftPosition": 781,
    "Rank": 244
  },
  {
    "Name": "Rasheed Bailey",
    "Team": "CAR",
    "Position": "WR",
    "ByeWeek": 4,
    "Age": 25,
    "RushingYards": 2,
    "RushingTouchdowns": 0,
    "Receptions": 0,
    "ReceivingYards": 98,
    "ReceivingTouchdowns": 0,
    "FantasyPoints": 10,
    "AverageDraftPosition": 789,
    "Rank": 245
  },
  {
    "Name": "Jordan Leslie",
    "Team": "DEN",
    "Position": "WR",
    "ByeWeek": 10,
    "Age": 26,
    "RushingYards": 0,
    "RushingTouchdowns": 0,
    "Receptions": 5,
    "ReceivingYards": 71,
    "ReceivingTouchdowns": 1,
    "FantasyPoints": 13.1,
    "AverageDraftPosition": 798,
    "Rank": 246
  },
  {
    "Name": "Jamaal Jones",
    "Team": "CAR",
    "Position": "WR",
    "ByeWeek": 4,
    "Age": 25,
    "RushingYards": 1,
    "RushingTouchdowns": 0,
    "Receptions": 0,
    "ReceivingYards": 80,
    "ReceivingTouchdowns": 0,
    "FantasyPoints": 8.1,
    "AverageDraftPosition": 807,
    "Rank": 247
  },
  {
    "Name": "Marcus Tucker",
    "Team": "PIT",
    "Position": "WR",
    "ByeWeek": 7,
    "Age": 26,
    "RushingYards": 0,
    "RushingTouchdowns": 0,
    "Receptions": 0,
    "ReceivingYards": 132,
    "ReceivingTouchdowns": 0,
    "FantasyPoints": 13.2,
    "AverageDraftPosition": 819,
    "Rank": 248
  },
  {
    "Name": "KJ Brent",
    "Team": "IND",
    "Position": "WR",
    "ByeWeek": 9,
    "Age": 24,
    "RushingYards": 0,
    "RushingTouchdowns": 0,
    "Receptions": 1,
    "ReceivingYards": 18,
    "ReceivingTouchdowns": 0,
    "FantasyPoints": 1.8,
    "AverageDraftPosition": 821,
    "Rank": 249
  },
  {
    "Name": "Marquis Bundy",
    "Team": "NYG",
    "Position": "WR",
    "ByeWeek": 9,
    "Age": 24,
    "RushingYards": 0,
    "RushingTouchdowns": 0,
    "Receptions": 5,
    "ReceivingYards": 63,
    "ReceivingTouchdowns": 0,
    "FantasyPoints": 6.3,
    "AverageDraftPosition": 824,
    "Rank": 250
  },
  {
    "Name": "Cyril Grayson",
    "Team": "SEA",
    "Position": "WR",
    "ByeWeek": 7,
    "Age": 24,
    "RushingYards": 3,
    "RushingTouchdowns": 0,
    "Receptions": 0,
    "ReceivingYards": 154,
    "ReceivingTouchdowns": 1,
    "FantasyPoints": 21.7,
    "AverageDraftPosition": 826,
    "Rank": 251
  },
  {
    "Name": "Malachi Dupre",
    "Team": "BUF",
    "Position": "WR",
    "ByeWeek": 11,
    "Age": 22,
    "RushingYards": 0,
    "RushingTouchdowns": 0,
    "Receptions": 0,
    "ReceivingYards": 0,
    "ReceivingTouchdowns": 0,
    "FantasyPoints": 0,
    "AverageDraftPosition": 829,
    "Rank": 252
  },
  {
    "Name": "Trey Griffey",
    "Team": "PIT",
    "Position": "WR",
    "ByeWeek": 7,
    "Age": 24,
    "RushingYards": 2,
    "RushingTouchdowns": 0,
    "Receptions": 0,
    "ReceivingYards": 96,
    "ReceivingTouchdowns": 1,
    "FantasyPoints": 15.8,
    "AverageDraftPosition": 837,
    "Rank": 253
  },
  {
    "Name": "Quincy Adeboyejo",
    "Team": "BAL",
    "Position": "WR",
    "ByeWeek": 10,
    "Age": 23,
    "RushingYards": 2,
    "RushingTouchdowns": 0,
    "Receptions": 1,
    "ReceivingYards": 6,
    "ReceivingTouchdowns": 0,
    "FantasyPoints": 0.8,
    "AverageDraftPosition": 842,
    "Rank": 254
  },
  {
    "Name": "Austin Duke",
    "Team": "CAR",
    "Position": "WR",
    "ByeWeek": 4,
    "Age": 25,
    "RushingYards": 2,
    "RushingTouchdowns": 0,
    "Receptions": 0,
    "ReceivingYards": 76,
    "ReceivingTouchdowns": 0,
    "FantasyPoints": 7.8,
    "AverageDraftPosition": 847,
    "Rank": 255
  },
  {
    "Name": "Fred Ross",
    "Team": "CAR",
    "Position": "WR",
    "ByeWeek": 4,
    "Age": 23,
    "RushingYards": 0,
    "RushingTouchdowns": 0,
    "Receptions": 0,
    "ReceivingYards": 0,
    "ReceivingTouchdowns": 0,
    "FantasyPoints": 0,
    "AverageDraftPosition": 848,
    "Rank": 256
  },
  {
    "Name": "Michael Clark",
    "Team": "GB",
    "Position": "WR",
    "ByeWeek": 7,
    "Age": 22,
    "RushingYards": 2,
    "RushingTouchdowns": 0,
    "Receptions": 8,
    "ReceivingYards": 80,
    "ReceivingTouchdowns": 0,
    "FantasyPoints": 8.2,
    "AverageDraftPosition": 851,
    "Rank": 257
  },
  {
    "Name": "Cody Hollister",
    "Team": "NE",
    "Position": "WR",
    "ByeWeek": 11,
    "Age": 24,
    "RushingYards": 3,
    "RushingTouchdowns": 0,
    "Receptions": 0,
    "ReceivingYards": 146,
    "ReceivingTouchdowns": 0,
    "FantasyPoints": 14.9,
    "AverageDraftPosition": 858,
    "Rank": 258
  },
  {
    "Name": "Keon Hatcher",
    "Team": "OAK",
    "Position": "WR",
    "ByeWeek": 7,
    "Age": 23,
    "RushingYards": 4,
    "RushingTouchdowns": 0,
    "Receptions": 0,
    "ReceivingYards": 202,
    "ReceivingTouchdowns": 1,
    "FantasyPoints": 26.6,
    "AverageDraftPosition": 863,
    "Rank": 259
  },
  {
    "Name": "Isaac Whitney",
    "Team": "OAK",
    "Position": "WR",
    "ByeWeek": 7,
    "Age": 24,
    "RushingYards": 2,
    "RushingTouchdowns": 0,
    "Receptions": 4,
    "ReceivingYards": 105,
    "ReceivingTouchdowns": 0,
    "FantasyPoints": 10.7,
    "AverageDraftPosition": 865,
    "Rank": 260
  },
  {
    "Name": "Victor Bolden Jr.",
    "Team": "SF",
    "Position": "WR",
    "ByeWeek": 11,
    "Age": 23,
    "RushingYards": 0,
    "RushingTouchdowns": 0,
    "Receptions": 4,
    "ReceivingYards": 53,
    "ReceivingTouchdowns": 0,
    "FantasyPoints": 5.3,
    "AverageDraftPosition": 866,
    "Rank": 261
  },
  {
    "Name": "Marcus Kemp",
    "Team": "KC",
    "Position": "WR",
    "ByeWeek": 12,
    "Age": 22,
    "RushingYards": 4,
    "RushingTouchdowns": 0,
    "Receptions": 0,
    "ReceivingYards": 86,
    "ReceivingTouchdowns": 0,
    "FantasyPoints": 9,
    "AverageDraftPosition": 869,
    "Rank": 262
  },
  {
    "Name": "Krishawn Hogan",
    "Team": "IND",
    "Position": "WR",
    "ByeWeek": 9,
    "Age": 23,
    "RushingYards": 0,
    "RushingTouchdowns": 0,
    "Receptions": 5,
    "ReceivingYards": 64,
    "ReceivingTouchdowns": 0,
    "FantasyPoints": 6.4,
    "AverageDraftPosition": 873,
    "Rank": 263
  },
  {
    "Name": "Colby Pearson",
    "Team": "ATL",
    "Position": "WR",
    "ByeWeek": 8,
    "Age": 23,
    "RushingYards": 5,
    "RushingTouchdowns": 0,
    "Receptions": 0,
    "ReceivingYards": 237,
    "ReceivingTouchdowns": 1,
    "FantasyPoints": 30.2,
    "AverageDraftPosition": 902,
    "Rank": 264
  },
  {
    "Name": "Fred Brown",
    "Team": "LAR",
    "Position": "WR",
    "ByeWeek": 12,
    "Age": 24,
    "RushingYards": 2,
    "RushingTouchdowns": 0,
    "Receptions": 0,
    "ReceivingYards": 170,
    "ReceivingTouchdowns": 1,
    "FantasyPoints": 23.2,
    "AverageDraftPosition": 905,
    "Rank": 265
  },
  {
    "Name": "Rashard Davis",
    "Team": "PHI",
    "Position": "WR",
    "ByeWeek": 9,
    "Age": 22,
    "RushingYards": 4,
    "RushingTouchdowns": 0,
    "Receptions": 0,
    "ReceivingYards": 125,
    "ReceivingTouchdowns": 0,
    "FantasyPoints": 12.9,
    "AverageDraftPosition": 910,
    "Rank": 266
  },
  {
    "Name": "Josh Huff",
    "Team": "NO",
    "Position": "WR",
    "ByeWeek": 6,
    "Age": 26,
    "RushingYards": 0,
    "RushingTouchdowns": 0,
    "Receptions": 0,
    "ReceivingYards": 0,
    "ReceivingTouchdowns": 0,
    "FantasyPoints": 0,
    "AverageDraftPosition": 920,
    "Rank": 267
  },
  {
    "Name": "DeVier Posey",
    "Team": "BAL",
    "Position": "WR",
    "ByeWeek": 10,
    "Age": 28,
    "RushingYards": 0,
    "RushingTouchdowns": 0,
    "Receptions": 1,
    "ReceivingYards": 15,
    "ReceivingTouchdowns": 0,
    "FantasyPoints": 1.5,
    "AverageDraftPosition": 922,
    "Rank": 268
  },
  {
    "Name": "Griff Whalen",
    "Team": "OAK",
    "Position": "WR",
    "ByeWeek": 7,
    "Age": 28,
    "RushingYards": 0,
    "RushingTouchdowns": 0,
    "Receptions": 1,
    "ReceivingYards": 10,
    "ReceivingTouchdowns": 0,
    "FantasyPoints": 1,
    "AverageDraftPosition": 925,
    "Rank": 269
  },
  {
    "Name": "Justin Thomas",
    "Team": "PIT",
    "Position": "WR",
    "ByeWeek": 7,
    "Age": 24,
    "RushingYards": 3,
    "RushingTouchdowns": 0,
    "Receptions": 0,
    "ReceivingYards": 117,
    "ReceivingTouchdowns": 0,
    "FantasyPoints": 12,
    "AverageDraftPosition": 929,
    "Rank": 270
  },
  {
    "Name": "Marlon Brown",
    "Team": "CHI",
    "Position": "WR",
    "ByeWeek": 5,
    "Age": 27,
    "RushingYards": 0,
    "RushingTouchdowns": 0,
    "Receptions": 1,
    "ReceivingYards": 15,
    "ReceivingTouchdowns": 0,
    "FantasyPoints": 1.5,
    "AverageDraftPosition": 935,
    "Rank": 271
  },
  {
    "Name": "Cedrick Wilson",
    "Team": "DAL",
    "Position": "WR",
    "ByeWeek": 8,
    "Age": 22,
    "RushingYards": 0,
    "RushingTouchdowns": 0,
    "Receptions": 2,
    "ReceivingYards": 32,
    "ReceivingTouchdowns": 0,
    "FantasyPoints": 3.2,
    "AverageDraftPosition": 942,
    "Rank": 272
  },
  {
    "Name": "Trent Sherfield",
    "Team": "ARI",
    "Position": "WR",
    "ByeWeek": 9,
    "Age": 22,
    "RushingYards": 6,
    "RushingTouchdowns": 0,
    "Receptions": 0,
    "ReceivingYards": 195,
    "ReceivingTouchdowns": 1,
    "FantasyPoints": 26.1,
    "AverageDraftPosition": 994,
    "Rank": 273
  },
  {
    "Name": "Marchie Murdock",
    "Team": "DAL",
    "Position": "WR",
    "ByeWeek": 8,
    "Age": 23,
    "RushingYards": 3,
    "RushingTouchdowns": 0,
    "Receptions": 0,
    "ReceivingYards": 91,
    "ReceivingTouchdowns": 0,
    "FantasyPoints": 9.4,
    "AverageDraftPosition": 1008,
    "Rank": 274
  },
  {
    "Name": "Jalen Tolliver",
    "Team": "ARI",
    "Position": "WR",
    "ByeWeek": 9,
    "Age": 22,
    "RushingYards": 2,
    "RushingTouchdowns": 0,
    "Receptions": 0,
    "ReceivingYards": 150,
    "ReceivingTouchdowns": 1,
    "FantasyPoints": 21.2,
    "AverageDraftPosition": 1027,
    "Rank": 275
  },
  {
    "Name": "Byron Pringle",
    "Team": "KC",
    "Position": "WR",
    "ByeWeek": 12,
    "Age": 24,
    "RushingYards": 3,
    "RushingTouchdowns": 0,
    "Receptions": 0,
    "ReceivingYards": 129,
    "ReceivingTouchdowns": 0,
    "FantasyPoints": 13.2,
    "AverageDraftPosition": 1041,
    "Rank": 276
  },
  {
    "Name": "Caleb Scott",
    "Team": "SEA",
    "Position": "WR",
    "ByeWeek": 7,
    "Age": 22,
    "RushingYards": 6,
    "RushingTouchdowns": 0,
    "Receptions": 0,
    "ReceivingYards": 177,
    "ReceivingTouchdowns": 1,
    "FantasyPoints": 24.3,
    "AverageDraftPosition": 1043,
    "Rank": 277
  },
  {
    "Name": "Quadree Henderson",
    "Team": "PIT",
    "Position": "WR",
    "ByeWeek": 7,
    "Age": 21,
    "RushingYards": 4,
    "RushingTouchdowns": 0,
    "Receptions": 0,
    "ReceivingYards": 125,
    "ReceivingTouchdowns": 0,
    "FantasyPoints": 12.9,
    "AverageDraftPosition": 1048,
    "Rank": 278
  },
  {
    "Name": "Brandon Powell",
    "Team": "DET",
    "Position": "WR",
    "ByeWeek": 6,
    "Age": 21,
    "RushingYards": 0,
    "RushingTouchdowns": 0,
    "Receptions": 0,
    "ReceivingYards": 106,
    "ReceivingTouchdowns": 0,
    "FantasyPoints": 10.6,
    "AverageDraftPosition": 1101,
    "Rank": 279
  },
  {
    "Name": "Greg Little",
    "Team": "ARI",
    "Position": "WR",
    "ByeWeek": 9,
    "Age": 29,
    "RushingYards": 0,
    "RushingTouchdowns": 0,
    "Receptions": 0,
    "ReceivingYards": 0,
    "ReceivingTouchdowns": 0,
    "FantasyPoints": 0,
    "AverageDraftPosition": 1138,
    "Rank": 280
  },
  {
    "Name": "Andre Roberts",
    "Team": "NYJ",
    "Position": "WR",
    "ByeWeek": 11,
    "Age": 30,
    "RushingYards": 0,
    "RushingTouchdowns": 0,
    "Receptions": 1,
    "ReceivingYards": 15,
    "ReceivingTouchdowns": 0,
    "FantasyPoints": -0.5,
    "AverageDraftPosition": 1140,
    "Rank": 281
  },
  {
    "Name": "Isaiah McKenzie",
    "Team": "DEN",
    "Position": "WR",
    "ByeWeek": 10,
    "Age": 23,
    "RushingYards": 1,
    "RushingTouchdowns": 0,
    "Receptions": 4,
    "ReceivingYards": 109,
    "ReceivingTouchdowns": 1,
    "FantasyPoints": 17,
    "AverageDraftPosition": 1141,
    "Rank": 282
  },
  {
    "Name": "KD Cannon",
    "Team": "DAL",
    "Position": "WR",
    "ByeWeek": 8,
    "Age": 22,
    "RushingYards": 4,
    "RushingTouchdowns": 0,
    "Receptions": 0,
    "ReceivingYards": 134,
    "ReceivingTouchdowns": 0,
    "FantasyPoints": 13.8,
    "AverageDraftPosition": 1142,
    "Rank": 283
  }
]